{
"traceEvents": [
{"name":"Camera::RecalculateView","cat":"function","ph":"X","ts":19,"dur":15,"pid":1,"tid":0},
{"name":"Camera::RecalculateView","cat":"function","ph":"X","ts":5537,"dur":22,"pid":1,"tid":0},
{"name":"Camera::RecalculateView","cat":"function","ph":"X","ts":41346,"dur":21,"pid":1,"tid":0},
{"name":"Camera::RecalculateView","cat":"function","ph":"X","ts":44978,"dur":19,"pid":1,"tid":0},
{"name":"Camera::RecalculateView","cat":"function","ph":"X","ts":51048,"dur":17,"pid":1,"tid":0},
{"name":"Camera::RecalculateView","cat":"function","ph":"X","ts":51145,"dur":7,"pid":1,"tid":0},
{"name":"Camera::RecalculateView","cat":"function","ph":"X","ts":68757,"dur":18,"pid":1,"tid":0},
{"name":"Camera::RecalculateView","cat":"function","ph":"X","ts":69235,"dur":21,"pid":1,"tid":0},
{"name":"Camera::RecalculateView","cat":"function","ph":"X","ts":84508,"dur":18,"pid":1,"tid":0},
{"name":"Camera::RecalculateView","cat":"function","ph":"X","ts":84593,"dur":6,"pid":1,"tid":0},
{"name":"Camera::RecalculateView","cat":"function","ph":"X","ts":101550,"dur":17,"pid":1,"tid":0},
{"name":"Camera::RecalculateView","cat":"function","ph":"X","ts":118198,"dur":20,"pid":1,"tid":0},
{"name":"Camera::RecalculateView","cat":"function","ph":"X","ts":134227,"dur":17,"pid":1,"tid":0},
{"name":"Camera::RecalculateView","cat":"function","ph":"X","ts":151536,"dur":18,"pid":1,"tid":0},
{"name":"Camera::RecalculateView","cat":"function","ph":"X","ts":152004,"dur":15,"pid":1,"tid":0},
{"name":"Camera::RecalculateView","cat":"function","ph":"X","ts":152090,"dur":6,"pid":1,"tid":0},
{"name":"Camera::RecalculateView","cat":"function","ph":"X","ts":168714,"dur":25,"pid":1,"tid":0},
{"name":"Camera::RecalculateView","cat":"function","ph":"X","ts":168844,"dur":12,"pid":1,"tid":0},
{"name":"Camera::RecalculateView","cat":"function","ph":"X","ts":184667,"dur":18,"pid":1,"tid":0},
{"name":"Camera::RecalculateView","cat":"function","ph":"X","ts":184751,"dur":9,"pid":1,"tid":0},
{"name":"Camera::RecalculateView","cat":"function","ph":"X","ts":201962,"dur":15,"pid":1,"tid":0},
{"name":"Camera::RecalculateView","cat":"function","ph":"X","ts":202049,"dur":6,"pid":1,"tid":0},
{"name":"Camera::RecalculateView","cat":"function","ph":"X","ts":220368,"dur":17,"pid":1,"tid":0},
{"name":"Camera::RecalculateView","cat":"function","ph":"X","ts":220458,"dur":7,"pid":1,"tid":0},
{"name":"Camera::RecalculateView","cat":"function","ph":"X","ts":233909,"dur":16,"pid":1,"tid":0},
{"name":"Camera::RecalculateView","cat":"function","ph":"X","ts":233977,"dur":6,"pid":1,"tid":0},
{"name":"Camera::RecalculateView","cat":"function","ph":"X","ts":251197,"dur":19,"pid":1,"tid":0},
{"name":"Camera::RecalculateView","cat":"function","ph":"X","ts":251285,"dur":6,"pid":1,"tid":0},
{"name":"Camera::RecalculateView","cat":"function","ph":"X","ts":268417,"dur":18,"pid":1,"tid":0},
{"name":"Camera::RecalculateView","cat":"function","ph":"X","ts":268569,"dur":7,"pid":1,"tid":0},
{"name":"Camera::RecalculateView","cat":"function","ph":"X","ts":284985,"dur":22,"pid":1,"tid":0},
{"name":"Camera::RecalculateView","cat":"function","ph":"X","ts":285083,"dur":7,"pid":1,"tid":0},
{"name":"Camera::RecalculateView","cat":"function","ph":"X","ts":301275,"dur":22,"pid":1,"tid":0},
{"name":"Camera::RecalculateView","cat":"function","ph":"X","ts":301385,"dur":11,"pid":1,"tid":0},
{"name":"Camera::RecalculateView","cat":"function","ph":"X","ts":318245,"dur":19,"pid":1,"tid":0},
{"name":"Camera::RecalculateView","cat":"function","ph":"X","ts":318325,"dur":6,"pid":1,"tid":0},
{"name":"Camera::RecalculateView","cat":"function","ph":"X","ts":335209,"dur":19,"pid":1,"tid":0},
{"name":"Camera::RecalculateView","cat":"function","ph":"X","ts":335626,"dur":16,"pid":1,"tid":0},
{"name":"Camera::RecalculateView","cat":"function","ph":"X","ts":335723,"dur":7,"pid":1,"tid":0},
{"name":"Camera::RecalculateView","cat":"function","ph":"X","ts":351414,"dur":17,"pid":1,"tid":0},
{"name":"Camera::RecalculateView","cat":"function","ph":"X","ts":351500,"dur":6,"pid":1,"tid":0},
{"name":"Camera::RecalculateView","cat":"function","ph":"X","ts":368700,"dur":20,"pid":1,"tid":0},
{"name":"Camera::RecalculateView","cat":"function","ph":"X","ts":368799,"dur":7,"pid":1,"tid":0},
{"name":"Camera::RecalculateView","cat":"function","ph":"X","ts":384942,"dur":19,"pid":1,"tid":0},
{"name":"Camera::RecalculateView","cat":"function","ph":"X","ts":385039,"dur":6,"pid":1,"tid":0},
{"name":"Camera::RecalculateView","cat":"function","ph":"X","ts":401519,"dur":18,"pid":1,"tid":0},
{"name":"Camera::RecalculateView","cat":"function","ph":"X","ts":401609,"dur":6,"pid":1,"tid":0},
{"name":"Camera::RecalculateView","cat":"function","ph":"X","ts":418242,"dur":21,"pid":1,"tid":0},
{"name":"Camera::RecalculateView","cat":"function","ph":"X","ts":418489,"dur":28,"pid":1,"tid":0},
{"name":"Camera::RecalculateView","cat":"function","ph":"X","ts":435190,"dur":24,"pid":1,"tid":0},
{"name":"Camera::RecalculateView","cat":"function","ph":"X","ts":435321,"dur":10,"pid":1,"tid":0},
{"name":"Camera::RecalculateView","cat":"function","ph":"X","ts":451636,"dur":18,"pid":1,"tid":0},
{"name":"Camera::RecalculateView","cat":"function","ph":"X","ts":451726,"dur":8,"pid":1,"tid":0},
{"name":"Camera::RecalculateView","cat":"function","ph":"X","ts":468405,"dur":18,"pid":1,"tid":0},
{"name":"Camera::RecalculateView","cat":"function","ph":"X","ts":468495,"dur":6,"pid":1,"tid":0},
{"name":"Camera::RecalculateView","cat":"function","ph":"X","ts":484946,"dur":19,"pid":1,"tid":0},
{"name":"Camera::RecalculateView","cat":"function","ph":"X","ts":501749,"dur":20,"pid":1,"tid":0},
{"name":"Camera::RecalculateView","cat":"function","ph":"X","ts":501855,"dur":7,"pid":1,"tid":0},
{"name":"Camera::RecalculateView","cat":"function","ph":"X","ts":518714,"dur":19,"pid":1,"tid":0},
{"name":"Camera::RecalculateView","cat":"function","ph":"X","ts":518811,"dur":6,"pid":1,"tid":0},
{"name":"Camera::RecalculateView","cat":"function","ph":"X","ts":534460,"dur":19,"pid":1,"tid":0},
{"name":"Camera::RecalculateView","cat":"function","ph":"X","ts":534545,"dur":7,"pid":1,"tid":0},
{"name":"Camera::RecalculateView","cat":"function","ph":"X","ts":551417,"dur":19,"pid":1,"tid":0},
{"name":"Camera::RecalculateView","cat":"function","ph":"X","ts":551992,"dur":16,"pid":1,"tid":0},
{"name":"Camera::RecalculateView","cat":"function","ph":"X","ts":552115,"dur":7,"pid":1,"tid":0},
{"name":"Camera::RecalculateView","cat":"function","ph":"X","ts":568112,"dur":15,"pid":1,"tid":0},
{"name":"Camera::RecalculateView","cat":"function","ph":"X","ts":568189,"dur":6,"pid":1,"tid":0},
{"name":"Camera::RecalculateView","cat":"function","ph":"X","ts":584631,"dur":16,"pid":1,"tid":0},
{"name":"Camera::RecalculateView","cat":"function","ph":"X","ts":584715,"dur":6,"pid":1,"tid":0},
{"name":"Camera::RecalculateView","cat":"function","ph":"X","ts":601481,"dur":18,"pid":1,"tid":0},
{"name":"Camera::RecalculateView","cat":"function","ph":"X","ts":601571,"dur":6,"pid":1,"tid":0},
{"name":"Camera::RecalculateView","cat":"function","ph":"X","ts":617770,"dur":16,"pid":1,"tid":0},
{"name":"Camera::RecalculateView","cat":"function","ph":"X","ts":617856,"dur":6,"pid":1,"tid":0},
{"name":"Camera::RecalculateView","cat":"function","ph":"X","ts":635362,"dur":17,"pid":1,"tid":0},
{"name":"Camera::RecalculateView","cat":"function","ph":"X","ts":635446,"dur":6,"pid":1,"tid":0},
{"name":"Camera::RecalculateView","cat":"function","ph":"X","ts":651547,"dur":19,"pid":1,"tid":0},
{"name":"Camera::RecalculateView","cat":"function","ph":"X","ts":651635,"dur":6,"pid":1,"tid":0},
{"name":"Camera::RecalculateView","cat":"function","ph":"X","ts":671836,"dur":26,"pid":1,"tid":0},
{"name":"Camera::RecalculateView","cat":"function","ph":"X","ts":672735,"dur":22,"pid":1,"tid":0},
{"name":"Camera::RecalculateView","cat":"function","ph":"X","ts":672842,"dur":7,"pid":1,"tid":0},
{"name":"Camera::RecalculateView","cat":"function","ph":"X","ts":685628,"dur":37,"pid":1,"tid":0},
{"name":"Camera::RecalculateView","cat":"function","ph":"X","ts":685783,"dur":15,"pid":1,"tid":0},
{"name":"Camera::RecalculateView","cat":"function","ph":"X","ts":703239,"dur":26,"pid":1,"tid":0},
{"name":"Camera::RecalculateView","cat":"function","ph":"X","ts":703837,"dur":18,"pid":1,"tid":0},
{"name":"Camera::RecalculateView","cat":"function","ph":"X","ts":703939,"dur":6,"pid":1,"tid":0},
{"name":"Camera::RecalculateView","cat":"function","ph":"X","ts":718572,"dur":17,"pid":1,"tid":0},
{"name":"Camera::RecalculateView","cat":"function","ph":"X","ts":718666,"dur":10,"pid":1,"tid":0},
{"name":"Camera::RecalculateView","cat":"function","ph":"X","ts":736633,"dur":23,"pid":1,"tid":0},
{"name":"Camera::RecalculateView","cat":"function","ph":"X","ts":736836,"dur":9,"pid":1,"tid":0},
{"name":"Camera::RecalculateView","cat":"function","ph":"X","ts":752386,"dur":26,"pid":1,"tid":0},
{"name":"Camera::RecalculateView","cat":"function","ph":"X","ts":752506,"dur":14,"pid":1,"tid":0},
{"name":"Camera::RecalculateView","cat":"function","ph":"X","ts":768994,"dur":21,"pid":1,"tid":0},
{"name":"Camera::RecalculateView","cat":"function","ph":"X","ts":769096,"dur":7,"pid":1,"tid":0},
{"name":"Camera::RecalculateView","cat":"function","ph":"X","ts":787028,"dur":21,"pid":1,"tid":0},
{"name":"Camera::RecalculateView","cat":"function","ph":"X","ts":801728,"dur":19,"pid":1,"tid":0},
{"name":"Camera::RecalculateView","cat":"function","ph":"X","ts":821521,"dur":24,"pid":1,"tid":0},
{"name":"Camera::RecalculateView","cat":"function","ph":"X","ts":821748,"dur":19,"pid":1,"tid":0},
{"name":"Camera::RecalculateView","cat":"function","ph":"X","ts":837725,"dur":26,"pid":1,"tid":0},
{"name":"Camera::RecalculateView","cat":"function","ph":"X","ts":837876,"dur":18,"pid":1,"tid":0},
{"name":"Camera::RecalculateView","cat":"function","ph":"X","ts":852092,"dur":19,"pid":1,"tid":0},
{"name":"Camera::RecalculateView","cat":"function","ph":"X","ts":852187,"dur":7,"pid":1,"tid":0},
{"name":"Camera::RecalculateView","cat":"function","ph":"X","ts":869751,"dur":27,"pid":1,"tid":0},
{"name":"Camera::RecalculateView","cat":"function","ph":"X","ts":870234,"dur":22,"pid":1,"tid":0},
{"name":"Camera::RecalculateView","cat":"function","ph":"X","ts":885508,"dur":23,"pid":1,"tid":0},
{"name":"Camera::RecalculateView","cat":"function","ph":"X","ts":885625,"dur":6,"pid":1,"tid":0},
{"name":"Camera::RecalculateView","cat":"function","ph":"X","ts":902814,"dur":21,"pid":1,"tid":0},
{"name":"Camera::RecalculateView","cat":"function","ph":"X","ts":903016,"dur":9,"pid":1,"tid":0},
{"name":"Camera::RecalculateView","cat":"function","ph":"X","ts":919799,"dur":21,"pid":1,"tid":0},
{"name":"Camera::RecalculateView","cat":"function","ph":"X","ts":919895,"dur":10,"pid":1,"tid":0},
{"name":"Camera::RecalculateView","cat":"function","ph":"X","ts":938760,"dur":35,"pid":1,"tid":0},
{"name":"Camera::RecalculateView","cat":"function","ph":"X","ts":949533,"dur":21,"pid":1,"tid":0},
{"name":"Camera::RecalculateView","cat":"function","ph":"X","ts":954183,"dur":22,"pid":1,"tid":0},
{"name":"Camera::RecalculateView","cat":"function","ph":"X","ts":955692,"dur":21,"pid":1,"tid":0},
{"name":"Camera::GetForward","cat":"function","ph":"X","ts":966227,"dur":15,"pid":1,"tid":0},
{"name":"Camera::RecalculateView","cat":"function","ph":"X","ts":966250,"dur":9,"pid":1,"tid":0},
{"name":"Camera::RecalculateView","cat":"function","ph":"X","ts":968218,"dur":22,"pid":1,"tid":0},
{"name":"Camera::GetForward","cat":"function","ph":"X","ts":982976,"dur":17,"pid":1,"tid":0},
{"name":"Camera::RecalculateView","cat":"function","ph":"X","ts":983003,"dur":9,"pid":1,"tid":0},
{"name":"Camera::RecalculateView","cat":"function","ph":"X","ts":984595,"dur":19,"pid":1,"tid":0},
{"name":"Camera::GetForward","cat":"function","ph":"X","ts":999645,"dur":17,"pid":1,"tid":0},
{"name":"Camera::RecalculateView","cat":"function","ph":"X","ts":999670,"dur":9,"pid":1,"tid":0},
{"name":"Camera::RecalculateView","cat":"function","ph":"X","ts":1001419,"dur":22,"pid":1,"tid":0},
{"name":"Camera::GetForward","cat":"function","ph":"X","ts":1016253,"dur":16,"pid":1,"tid":0},
{"name":"Camera::RecalculateView","cat":"function","ph":"X","ts":1016277,"dur":9,"pid":1,"tid":0},
{"name":"Camera::RecalculateView","cat":"function","ph":"X","ts":1017960,"dur":19,"pid":1,"tid":0},
{"name":"Camera::GetForward","cat":"function","ph":"X","ts":1032925,"dur":15,"pid":1,"tid":0},
{"name":"Camera::RecalculateView","cat":"function","ph":"X","ts":1032947,"dur":9,"pid":1,"tid":0},
{"name":"Camera::GetForward","cat":"function","ph":"X","ts":1049572,"dur":16,"pid":1,"tid":0},
{"name":"Camera::RecalculateView","cat":"function","ph":"X","ts":1049596,"dur":18,"pid":1,"tid":0},
{"name":"Camera::GetForward","cat":"function","ph":"X","ts":1066280,"dur":16,"pid":1,"tid":0},
{"name":"Camera::RecalculateView","cat":"function","ph":"X","ts":1066305,"dur":9,"pid":1,"tid":0},
{"name":"Camera::GetForward","cat":"function","ph":"X","ts":1082964,"dur":17,"pid":1,"tid":0},
{"name":"Camera::RecalculateView","cat":"function","ph":"X","ts":1082989,"dur":9,"pid":1,"tid":0},
{"name":"Camera::GetForward","cat":"function","ph":"X","ts":1099645,"dur":17,"pid":1,"tid":0},
{"name":"Camera::RecalculateView","cat":"function","ph":"X","ts":1099671,"dur":9,"pid":1,"tid":0},
{"name":"Camera::GetForward","cat":"function","ph":"X","ts":1116339,"dur":17,"pid":1,"tid":0},
{"name":"Camera::RecalculateView","cat":"function","ph":"X","ts":1116365,"dur":9,"pid":1,"tid":0},
{"name":"Camera::GetForward","cat":"function","ph":"X","ts":1133058,"dur":18,"pid":1,"tid":0},
{"name":"Camera::RecalculateView","cat":"function","ph":"X","ts":1133085,"dur":9,"pid":1,"tid":0},
{"name":"Camera::RecalculateView","cat":"function","ph":"X","ts":1141984,"dur":21,"pid":1,"tid":0},
{"name":"Camera::GetForward","cat":"function","ph":"X","ts":1149698,"dur":16,"pid":1,"tid":0},
{"name":"Camera::RecalculateView","cat":"function","ph":"X","ts":1149723,"dur":9,"pid":1,"tid":0},
{"name":"Camera::RecalculateView","cat":"function","ph":"X","ts":1155244,"dur":22,"pid":1,"tid":0},
{"name":"Camera::GetForward","cat":"function","ph":"X","ts":1166348,"dur":15,"pid":1,"tid":0},
{"name":"Camera::RecalculateView","cat":"function","ph":"X","ts":1166373,"dur":9,"pid":1,"tid":0},
{"name":"Camera::RecalculateView","cat":"function","ph":"X","ts":1169432,"dur":33,"pid":1,"tid":0},
{"name":"Camera::GetForward","cat":"function","ph":"X","ts":1183043,"dur":16,"pid":1,"tid":0},
{"name":"Camera::RecalculateView","cat":"function","ph":"X","ts":1183069,"dur":9,"pid":1,"tid":0},
{"name":"Camera::RecalculateView","cat":"function","ph":"X","ts":1186222,"dur":20,"pid":1,"tid":0},
{"name":"Camera::GetForward","cat":"function","ph":"X","ts":1199702,"dur":15,"pid":1,"tid":0},
{"name":"Camera::GetForward","cat":"function","ph":"X","ts":1199725,"dur":3,"pid":1,"tid":0},
{"name":"Camera::RecalculateView","cat":"function","ph":"X","ts":1199731,"dur":9,"pid":1,"tid":0},
{"name":"Camera::RecalculateView","cat":"function","ph":"X","ts":1201397,"dur":20,"pid":1,"tid":0},
{"name":"Camera::GetForward","cat":"function","ph":"X","ts":1216490,"dur":22,"pid":1,"tid":0},
{"name":"Camera::GetForward","cat":"function","ph":"X","ts":1216530,"dur":8,"pid":1,"tid":0},
{"name":"Camera::RecalculateView","cat":"function","ph":"X","ts":1216545,"dur":14,"pid":1,"tid":0},
{"name":"Camera::RecalculateView","cat":"function","ph":"X","ts":1221567,"dur":22,"pid":1,"tid":0},
{"name":"Camera::GetForward","cat":"function","ph":"X","ts":1233148,"dur":21,"pid":1,"tid":0},
{"name":"Camera::GetForward","cat":"function","ph":"X","ts":1233181,"dur":4,"pid":1,"tid":0},
{"name":"Camera::RecalculateView","cat":"function","ph":"X","ts":1233189,"dur":12,"pid":1,"tid":0},
{"name":"Camera::RecalculateView","cat":"function","ph":"X","ts":1235611,"dur":27,"pid":1,"tid":0},
{"name":"Camera::GetForward","cat":"function","ph":"X","ts":1249798,"dur":18,"pid":1,"tid":0},
{"name":"Camera::GetForward","cat":"function","ph":"X","ts":1249824,"dur":2,"pid":1,"tid":0},
{"name":"Camera::RecalculateView","cat":"function","ph":"X","ts":1249831,"dur":9,"pid":1,"tid":0},
{"name":"Camera::RecalculateView","cat":"function","ph":"X","ts":1252080,"dur":20,"pid":1,"tid":0},
{"name":"Camera::GetForward","cat":"function","ph":"X","ts":1266450,"dur":16,"pid":1,"tid":0},
{"name":"Camera::GetForward","cat":"function","ph":"X","ts":1266474,"dur":3,"pid":1,"tid":0},
{"name":"Camera::RecalculateView","cat":"function","ph":"X","ts":1266480,"dur":9,"pid":1,"tid":0},
{"name":"Camera::RecalculateView","cat":"function","ph":"X","ts":1268470,"dur":20,"pid":1,"tid":0},
{"name":"Camera::GetForward","cat":"function","ph":"X","ts":1283144,"dur":16,"pid":1,"tid":0},
{"name":"Camera::GetForward","cat":"function","ph":"X","ts":1283169,"dur":3,"pid":1,"tid":0},
{"name":"Camera::RecalculateView","cat":"function","ph":"X","ts":1283176,"dur":9,"pid":1,"tid":0},
{"name":"Camera::RecalculateView","cat":"function","ph":"X","ts":1285670,"dur":22,"pid":1,"tid":0},
{"name":"Camera::GetForward","cat":"function","ph":"X","ts":1299847,"dur":17,"pid":1,"tid":0},
{"name":"Camera::GetForward","cat":"function","ph":"X","ts":1299873,"dur":2,"pid":1,"tid":0},
{"name":"Camera::RecalculateView","cat":"function","ph":"X","ts":1299880,"dur":9,"pid":1,"tid":0},
{"name":"Camera::RecalculateView","cat":"function","ph":"X","ts":1301906,"dur":20,"pid":1,"tid":0},
{"name":"Camera::GetForward","cat":"function","ph":"X","ts":1316468,"dur":15,"pid":1,"tid":0},
{"name":"Camera::GetForward","cat":"function","ph":"X","ts":1316491,"dur":2,"pid":1,"tid":0},
{"name":"Camera::RecalculateView","cat":"function","ph":"X","ts":1316497,"dur":9,"pid":1,"tid":0},
{"name":"Camera::GetForward","cat":"function","ph":"X","ts":1333447,"dur":26,"pid":1,"tid":0},
{"name":"Camera::GetForward","cat":"function","ph":"X","ts":1333485,"dur":3,"pid":1,"tid":0},
{"name":"Camera::RecalculateView","cat":"function","ph":"X","ts":1333492,"dur":10,"pid":1,"tid":0},
{"name":"Camera::RecalculateView","cat":"function","ph":"X","ts":1335840,"dur":21,"pid":1,"tid":0},
{"name":"Camera::GetForward","cat":"function","ph":"X","ts":1349822,"dur":17,"pid":1,"tid":0},
{"name":"Camera::GetForward","cat":"function","ph":"X","ts":1349847,"dur":3,"pid":1,"tid":0},
{"name":"Camera::RecalculateView","cat":"function","ph":"X","ts":1349853,"dur":9,"pid":1,"tid":0},
{"name":"Camera::RecalculateView","cat":"function","ph":"X","ts":1356142,"dur":26,"pid":1,"tid":0},
{"name":"Camera::GetForward","cat":"function","ph":"X","ts":1366524,"dur":16,"pid":1,"tid":0},
{"name":"Camera::GetForward","cat":"function","ph":"X","ts":1366548,"dur":2,"pid":1,"tid":0},
{"name":"Camera::RecalculateView","cat":"function","ph":"X","ts":1366554,"dur":9,"pid":1,"tid":0},
{"name":"Camera::RecalculateView","cat":"function","ph":"X","ts":1368142,"dur":20,"pid":1,"tid":0},
{"name":"Camera::RecalculateView","cat":"function","ph":"X","ts":1369102,"dur":17,"pid":1,"tid":0},
{"name":"Camera::GetForward","cat":"function","ph":"X","ts":1383269,"dur":14,"pid":1,"tid":0},
{"name":"Camera::GetForward","cat":"function","ph":"X","ts":1383290,"dur":2,"pid":1,"tid":0},
{"name":"Camera::RecalculateView","cat":"function","ph":"X","ts":1383296,"dur":9,"pid":1,"tid":0},
{"name":"Camera::RecalculateView","cat":"function","ph":"X","ts":1385064,"dur":19,"pid":1,"tid":0},
{"name":"Camera::GetForward","cat":"function","ph":"X","ts":1399914,"dur":17,"pid":1,"tid":0},
{"name":"Camera::GetForward","cat":"function","ph":"X","ts":1399939,"dur":2,"pid":1,"tid":0},
{"name":"Camera::RecalculateView","cat":"function","ph":"X","ts":1399945,"dur":9,"pid":1,"tid":0},
{"name":"Camera::RecalculateView","cat":"function","ph":"X","ts":1401515,"dur":20,"pid":1,"tid":0},
{"name":"Camera::RecalculateView","cat":"function","ph":"X","ts":1402506,"dur":18,"pid":1,"tid":0},
{"name":"Camera::GetForward","cat":"function","ph":"X","ts":1416497,"dur":13,"pid":1,"tid":0},
{"name":"Camera::RecalculateView","cat":"function","ph":"X","ts":1416518,"dur":9,"pid":1,"tid":0},
{"name":"Camera::RecalculateView","cat":"function","ph":"X","ts":1418115,"dur":18,"pid":1,"tid":0},
{"name":"Camera::GetForward","cat":"function","ph":"X","ts":1433230,"dur":23,"pid":1,"tid":0},
{"name":"Camera::RecalculateView","cat":"function","ph":"X","ts":1433264,"dur":18,"pid":1,"tid":0},
{"name":"Camera::RecalculateView","cat":"function","ph":"X","ts":1435764,"dur":19,"pid":1,"tid":0},
{"name":"Camera::GetForward","cat":"function","ph":"X","ts":1449864,"dur":14,"pid":1,"tid":0},
{"name":"Camera::RecalculateView","cat":"function","ph":"X","ts":1449885,"dur":8,"pid":1,"tid":0},
{"name":"Camera::RecalculateView","cat":"function","ph":"X","ts":1451415,"dur":19,"pid":1,"tid":0},
{"name":"Camera::GetForward","cat":"function","ph":"X","ts":1466822,"dur":19,"pid":1,"tid":0},
{"name":"Camera::RecalculateView","cat":"function","ph":"X","ts":1466952,"dur":9,"pid":1,"tid":0},
{"name":"Camera::RecalculateView","cat":"function","ph":"X","ts":1468427,"dur":17,"pid":1,"tid":0},
{"name":"Camera::GetForward","cat":"function","ph":"X","ts":1483338,"dur":19,"pid":1,"tid":0},
{"name":"Camera::RecalculateView","cat":"function","ph":"X","ts":1483367,"dur":12,"pid":1,"tid":0},
{"name":"Camera::RecalculateView","cat":"function","ph":"X","ts":1485226,"dur":21,"pid":1,"tid":0},
{"name":"Camera::GetForward","cat":"function","ph":"X","ts":1500024,"dur":19,"pid":1,"tid":0},
{"name":"Camera::RecalculateView","cat":"function","ph":"X","ts":1500052,"dur":9,"pid":1,"tid":0},
{"name":"Camera::RecalculateView","cat":"function","ph":"X","ts":1504731,"dur":21,"pid":1,"tid":0},
{"name":"Camera::GetForward","cat":"function","ph":"X","ts":1516669,"dur":17,"pid":1,"tid":0},
{"name":"Camera::RecalculateView","cat":"function","ph":"X","ts":1516694,"dur":9,"pid":1,"tid":0},
{"name":"Camera::RecalculateView","cat":"function","ph":"X","ts":1522911,"dur":20,"pid":1,"tid":0},
{"name":"Camera::GetForward","cat":"function","ph":"X","ts":1533312,"dur":15,"pid":1,"tid":0},
{"name":"Camera::RecalculateView","cat":"function","ph":"X","ts":1533335,"dur":9,"pid":1,"tid":0},
{"name":"Camera::RecalculateView","cat":"function","ph":"X","ts":1535371,"dur":22,"pid":1,"tid":0},
{"name":"Camera::RecalculateView","cat":"function","ph":"X","ts":1535877,"dur":15,"pid":1,"tid":0},
{"name":"Camera::GetForward","cat":"function","ph":"X","ts":1550000,"dur":15,"pid":1,"tid":0},
{"name":"Camera::RecalculateView","cat":"function","ph":"X","ts":1550024,"dur":9,"pid":1,"tid":0},
{"name":"Camera::RecalculateView","cat":"function","ph":"X","ts":1551668,"dur":19,"pid":1,"tid":0},
{"name":"Camera::GetForward","cat":"function","ph":"X","ts":1566705,"dur":17,"pid":1,"tid":0},
{"name":"Camera::RecalculateView","cat":"function","ph":"X","ts":1566730,"dur":9,"pid":1,"tid":0},
{"name":"Camera::RecalculateView","cat":"function","ph":"X","ts":1570514,"dur":20,"pid":1,"tid":0},
{"name":"Camera::GetForward","cat":"function","ph":"X","ts":1583342,"dur":16,"pid":1,"tid":0},
{"name":"Camera::RecalculateView","cat":"function","ph":"X","ts":1583366,"dur":9,"pid":1,"tid":0},
{"name":"Camera::RecalculateView","cat":"function","ph":"X","ts":1584870,"dur":19,"pid":1,"tid":0},
{"name":"Camera::GetForward","cat":"function","ph":"X","ts":1600087,"dur":16,"pid":1,"tid":0},
{"name":"Camera::RecalculateView","cat":"function","ph":"X","ts":1600111,"dur":9,"pid":1,"tid":0},
{"name":"Camera::RecalculateView","cat":"function","ph":"X","ts":1601607,"dur":19,"pid":1,"tid":0},
{"name":"Camera::GetForward","cat":"function","ph":"X","ts":1616716,"dur":18,"pid":1,"tid":0},
{"name":"Camera::RecalculateView","cat":"function","ph":"X","ts":1616745,"dur":9,"pid":1,"tid":0},
{"name":"Camera::RecalculateView","cat":"function","ph":"X","ts":1618475,"dur":20,"pid":1,"tid":0},
{"name":"Camera::GetForward","cat":"function","ph":"X","ts":1633437,"dur":17,"pid":1,"tid":0},
{"name":"Camera::RecalculateView","cat":"function","ph":"X","ts":1633463,"dur":9,"pid":1,"tid":0},
{"name":"Camera::RecalculateView","cat":"function","ph":"X","ts":1635105,"dur":23,"pid":1,"tid":0},
{"name":"Camera::GetForward","cat":"function","ph":"X","ts":1650097,"dur":17,"pid":1,"tid":0},
{"name":"Camera::RecalculateView","cat":"function","ph":"X","ts":1650121,"dur":9,"pid":1,"tid":0},
{"name":"Camera::RecalculateView","cat":"function","ph":"X","ts":1651189,"dur":19,"pid":1,"tid":0},
{"name":"Camera::GetForward","cat":"function","ph":"X","ts":1666734,"dur":16,"pid":1,"tid":0},
{"name":"Camera::RecalculateView","cat":"function","ph":"X","ts":1666760,"dur":9,"pid":1,"tid":0},
{"name":"Camera::RecalculateView","cat":"function","ph":"X","ts":1668259,"dur":20,"pid":1,"tid":0},
{"name":"Camera::GetForward","cat":"function","ph":"X","ts":1683389,"dur":13,"pid":1,"tid":0},
{"name":"Camera::RecalculateView","cat":"function","ph":"X","ts":1683409,"dur":9,"pid":1,"tid":0},
{"name":"Camera::RecalculateView","cat":"function","ph":"X","ts":1684806,"dur":19,"pid":1,"tid":0},
{"name":"Camera::GetForward","cat":"function","ph":"X","ts":1700070,"dur":13,"pid":1,"tid":0},
{"name":"Camera::RecalculateView","cat":"function","ph":"X","ts":1700090,"dur":9,"pid":1,"tid":0},
{"name":"Camera::RecalculateView","cat":"function","ph":"X","ts":1701082,"dur":17,"pid":1,"tid":0},
{"name":"Camera::GetForward","cat":"function","ph":"X","ts":1716742,"dur":12,"pid":1,"tid":0},
{"name":"Camera::RecalculateView","cat":"function","ph":"X","ts":1716762,"dur":9,"pid":1,"tid":0},
{"name":"Camera::RecalculateView","cat":"function","ph":"X","ts":1718224,"dur":17,"pid":1,"tid":0},
{"name":"Camera::GetForward","cat":"function","ph":"X","ts":1733435,"dur":13,"pid":1,"tid":0},
{"name":"Camera::RecalculateView","cat":"function","ph":"X","ts":1733455,"dur":9,"pid":1,"tid":0},
{"name":"Camera::RecalculateView","cat":"function","ph":"X","ts":1736143,"dur":18,"pid":1,"tid":0},
{"name":"Camera::GetForward","cat":"function","ph":"X","ts":1750188,"dur":17,"pid":1,"tid":0},
{"name":"Camera::RecalculateView","cat":"function","ph":"X","ts":1750214,"dur":10,"pid":1,"tid":0},
{"name":"Camera::GetForward","cat":"function","ph":"X","ts":1766865,"dur":18,"pid":1,"tid":0},
{"name":"Camera::RecalculateView","cat":"function","ph":"X","ts":1766891,"dur":9,"pid":1,"tid":0},
{"name":"Camera::GetForward","cat":"function","ph":"X","ts":1783544,"dur":16,"pid":1,"tid":0},
{"name":"Camera::RecalculateView","cat":"function","ph":"X","ts":1783569,"dur":9,"pid":1,"tid":0},
{"name":"Camera::GetForward","cat":"function","ph":"X","ts":1800166,"dur":16,"pid":1,"tid":0},
{"name":"Camera::GetForward","cat":"function","ph":"X","ts":1800190,"dur":2,"pid":1,"tid":0},
{"name":"Camera::RecalculateView","cat":"function","ph":"X","ts":1800196,"dur":9,"pid":1,"tid":0},
{"name":"Camera::GetForward","cat":"function","ph":"X","ts":1816879,"dur":17,"pid":1,"tid":0},
{"name":"Camera::GetForward","cat":"function","ph":"X","ts":1816904,"dur":2,"pid":1,"tid":0},
{"name":"Camera::RecalculateView","cat":"function","ph":"X","ts":1816911,"dur":9,"pid":1,"tid":0},
{"name":"Camera::GetForward","cat":"function","ph":"X","ts":1833538,"dur":16,"pid":1,"tid":0},
{"name":"Camera::GetForward","cat":"function","ph":"X","ts":1833561,"dur":2,"pid":1,"tid":0},
{"name":"Camera::RecalculateView","cat":"function","ph":"X","ts":1833568,"dur":9,"pid":1,"tid":0},
{"name":"Camera::RecalculateView","cat":"function","ph":"X","ts":1835468,"dur":21,"pid":1,"tid":0},
{"name":"Camera::GetForward","cat":"function","ph":"X","ts":1850282,"dur":16,"pid":1,"tid":0},
{"name":"Camera::GetForward","cat":"function","ph":"X","ts":1850306,"dur":2,"pid":1,"tid":0},
{"name":"Camera::RecalculateView","cat":"function","ph":"X","ts":1850312,"dur":9,"pid":1,"tid":0},
{"name":"Camera::GetForward","cat":"function","ph":"X","ts":1866967,"dur":17,"pid":1,"tid":0},
{"name":"Camera::GetForward","cat":"function","ph":"X","ts":1866993,"dur":2,"pid":1,"tid":0},
{"name":"Camera::RecalculateView","cat":"function","ph":"X","ts":1867000,"dur":9,"pid":1,"tid":0},
{"name":"Camera::RecalculateView","cat":"function","ph":"X","ts":1869346,"dur":22,"pid":1,"tid":0},
{"name":"Camera::GetForward","cat":"function","ph":"X","ts":1883602,"dur":15,"pid":1,"tid":0},
{"name":"Camera::GetForward","cat":"function","ph":"X","ts":1883625,"dur":2,"pid":1,"tid":0},
{"name":"Camera::RecalculateView","cat":"function","ph":"X","ts":1883632,"dur":9,"pid":1,"tid":0},
{"name":"Camera::RecalculateView","cat":"function","ph":"X","ts":1885181,"dur":20,"pid":1,"tid":0},
{"name":"Camera::GetForward","cat":"function","ph":"X","ts":1900298,"dur":14,"pid":1,"tid":0},
{"name":"Camera::GetForward","cat":"function","ph":"X","ts":1900320,"dur":2,"pid":1,"tid":0},
{"name":"Camera::RecalculateView","cat":"function","ph":"X","ts":1900326,"dur":8,"pid":1,"tid":0},
{"name":"Camera::GetForward","cat":"function","ph":"X","ts":1916918,"dur":14,"pid":1,"tid":0},
{"name":"Camera::GetForward","cat":"function","ph":"X","ts":1916939,"dur":2,"pid":1,"tid":0},
{"name":"Camera::RecalculateView","cat":"function","ph":"X","ts":1916945,"dur":8,"pid":1,"tid":0},
{"name":"Camera::GetForward","cat":"function","ph":"X","ts":1933693,"dur":15,"pid":1,"tid":0},
{"name":"Camera::GetForward","cat":"function","ph":"X","ts":1933717,"dur":2,"pid":1,"tid":0},
{"name":"Camera::RecalculateView","cat":"function","ph":"X","ts":1933723,"dur":9,"pid":1,"tid":0},
{"name":"Camera::GetForward","cat":"function","ph":"X","ts":1950258,"dur":15,"pid":1,"tid":0},
{"name":"Camera::GetForward","cat":"function","ph":"X","ts":1950281,"dur":2,"pid":1,"tid":0},
{"name":"Camera::RecalculateView","cat":"function","ph":"X","ts":1950287,"dur":9,"pid":1,"tid":0},
{"name":"Camera::GetForward","cat":"function","ph":"X","ts":1966986,"dur":15,"pid":1,"tid":0},
{"name":"Camera::GetForward","cat":"function","ph":"X","ts":1967009,"dur":2,"pid":1,"tid":0},
{"name":"Camera::RecalculateView","cat":"function","ph":"X","ts":1967015,"dur":9,"pid":1,"tid":0},
{"name":"Camera::RecalculateView","cat":"function","ph":"X","ts":1968440,"dur":19,"pid":1,"tid":0},
{"name":"Camera::GetForward","cat":"function","ph":"X","ts":1983678,"dur":14,"pid":1,"tid":0},
{"name":"Camera::GetForward","cat":"function","ph":"X","ts":1983700,"dur":2,"pid":1,"tid":0},
{"name":"Camera::RecalculateView","cat":"function","ph":"X","ts":1983706,"dur":9,"pid":1,"tid":0},
{"name":"Camera::RecalculateView","cat":"function","ph":"X","ts":1985746,"dur":20,"pid":1,"tid":0},
{"name":"Camera::GetForward","cat":"function","ph":"X","ts":2000411,"dur":23,"pid":1,"tid":0},
{"name":"Camera::GetForward","cat":"function","ph":"X","ts":2000445,"dur":5,"pid":1,"tid":0},
{"name":"Camera::RecalculateView","cat":"function","ph":"X","ts":2000457,"dur":18,"pid":1,"tid":0},
{"name":"Camera::RecalculateView","cat":"function","ph":"X","ts":2002096,"dur":20,"pid":1,"tid":0},
{"name":"Camera::GetForward","cat":"function","ph":"X","ts":2017019,"dur":15,"pid":1,"tid":0},
{"name":"Camera::GetForward","cat":"function","ph":"X","ts":2017041,"dur":3,"pid":1,"tid":0},
{"name":"Camera::RecalculateView","cat":"function","ph":"X","ts":2017047,"dur":9,"pid":1,"tid":0},
{"name":"Camera::RecalculateView","cat":"function","ph":"X","ts":2018529,"dur":19,"pid":1,"tid":0},
{"name":"Camera::GetForward","cat":"function","ph":"X","ts":2033689,"dur":13,"pid":1,"tid":0},
{"name":"Camera::GetForward","cat":"function","ph":"X","ts":2033709,"dur":2,"pid":1,"tid":0},
{"name":"Camera::RecalculateView","cat":"function","ph":"X","ts":2033715,"dur":9,"pid":1,"tid":0},
{"name":"Camera::RecalculateView","cat":"function","ph":"X","ts":2035336,"dur":18,"pid":1,"tid":0},
{"name":"Camera::GetForward","cat":"function","ph":"X","ts":2050366,"dur":12,"pid":1,"tid":0},
{"name":"Camera::GetForward","cat":"function","ph":"X","ts":2050385,"dur":3,"pid":1,"tid":0},
{"name":"Camera::RecalculateView","cat":"function","ph":"X","ts":2050392,"dur":9,"pid":1,"tid":0},
{"name":"Camera::RecalculateView","cat":"function","ph":"X","ts":2052427,"dur":17,"pid":1,"tid":0},
{"name":"Camera::GetForward","cat":"function","ph":"X","ts":2067010,"dur":12,"pid":1,"tid":0},
{"name":"Camera::GetForward","cat":"function","ph":"X","ts":2067028,"dur":3,"pid":1,"tid":0},
{"name":"Camera::RecalculateView","cat":"function","ph":"X","ts":2067035,"dur":9,"pid":1,"tid":0},
{"name":"Camera::RecalculateView","cat":"function","ph":"X","ts":2068313,"dur":16,"pid":1,"tid":0},
{"name":"Camera::GetForward","cat":"function","ph":"X","ts":2083750,"dur":14,"pid":1,"tid":0},
{"name":"Camera::GetForward","cat":"function","ph":"X","ts":2083772,"dur":2,"pid":1,"tid":0},
{"name":"Camera::RecalculateView","cat":"function","ph":"X","ts":2083778,"dur":9,"pid":1,"tid":0},
{"name":"Camera::RecalculateView","cat":"function","ph":"X","ts":2085092,"dur":17,"pid":1,"tid":0},
{"name":"Camera::GetForward","cat":"function","ph":"X","ts":2100366,"dur":12,"pid":1,"tid":0},
{"name":"Camera::GetForward","cat":"function","ph":"X","ts":2100385,"dur":2,"pid":1,"tid":0},
{"name":"Camera::RecalculateView","cat":"function","ph":"X","ts":2100391,"dur":8,"pid":1,"tid":0},
{"name":"Camera::RecalculateView","cat":"function","ph":"X","ts":2102185,"dur":17,"pid":1,"tid":0},
{"name":"Camera::GetForward","cat":"function","ph":"X","ts":2117074,"dur":12,"pid":1,"tid":0},
{"name":"Camera::GetForward","cat":"function","ph":"X","ts":2117093,"dur":2,"pid":1,"tid":0},
{"name":"Camera::RecalculateView","cat":"function","ph":"X","ts":2117099,"dur":9,"pid":1,"tid":0},
{"name":"Camera::RecalculateView","cat":"function","ph":"X","ts":2118429,"dur":17,"pid":1,"tid":0},
{"name":"Camera::GetForward","cat":"function","ph":"X","ts":2133717,"dur":11,"pid":1,"tid":0},
{"name":"Camera::GetForward","cat":"function","ph":"X","ts":2133736,"dur":2,"pid":1,"tid":0},
{"name":"Camera::RecalculateView","cat":"function","ph":"X","ts":2133742,"dur":8,"pid":1,"tid":0},
{"name":"Camera::RecalculateView","cat":"function","ph":"X","ts":2135121,"dur":16,"pid":1,"tid":0},
{"name":"Camera::RecalculateView","cat":"function","ph":"X","ts":2135580,"dur":14,"pid":1,"tid":0},
{"name":"Camera::GetForward","cat":"function","ph":"X","ts":2150425,"dur":10,"pid":1,"tid":0},
{"name":"Camera::GetForward","cat":"function","ph":"X","ts":2150442,"dur":2,"pid":1,"tid":0},
{"name":"Camera::RecalculateView","cat":"function","ph":"X","ts":2150448,"dur":8,"pid":1,"tid":0},
{"name":"Camera::RecalculateView","cat":"function","ph":"X","ts":2151779,"dur":15,"pid":1,"tid":0},
{"name":"Camera::GetForward","cat":"function","ph":"X","ts":2167113,"dur":11,"pid":1,"tid":0},
{"name":"Camera::GetForward","cat":"function","ph":"X","ts":2167131,"dur":2,"pid":1,"tid":0},
{"name":"Camera::RecalculateView","cat":"function","ph":"X","ts":2167137,"dur":8,"pid":1,"tid":0},
{"name":"Camera::RecalculateView","cat":"function","ph":"X","ts":2168582,"dur":16,"pid":1,"tid":0},
{"name":"Camera::GetForward","cat":"function","ph":"X","ts":2183753,"dur":11,"pid":1,"tid":0},
{"name":"Camera::GetForward","cat":"function","ph":"X","ts":2183770,"dur":2,"pid":1,"tid":0},
{"name":"Camera::RecalculateView","cat":"function","ph":"X","ts":2183776,"dur":9,"pid":1,"tid":0},
{"name":"Camera::RecalculateView","cat":"function","ph":"X","ts":2185355,"dur":16,"pid":1,"tid":0},
{"name":"Camera::GetForward","cat":"function","ph":"X","ts":2200505,"dur":13,"pid":1,"tid":0},
{"name":"Camera::GetForward","cat":"function","ph":"X","ts":2200526,"dur":2,"pid":1,"tid":0},
{"name":"Camera::RecalculateView","cat":"function","ph":"X","ts":2200532,"dur":9,"pid":1,"tid":0},
{"name":"Camera::GetForward","cat":"function","ph":"X","ts":2217179,"dur":13,"pid":1,"tid":0},
{"name":"Camera::GetForward","cat":"function","ph":"X","ts":2217200,"dur":2,"pid":1,"tid":0},
{"name":"Camera::RecalculateView","cat":"function","ph":"X","ts":2217207,"dur":8,"pid":1,"tid":0},
{"name":"Camera::RecalculateView","cat":"function","ph":"X","ts":2218595,"dur":19,"pid":1,"tid":0},
{"name":"Camera::GetForward","cat":"function","ph":"X","ts":2233814,"dur":13,"pid":1,"tid":0},
{"name":"Camera::GetForward","cat":"function","ph":"X","ts":2233834,"dur":2,"pid":1,"tid":0},
{"name":"Camera::RecalculateView","cat":"function","ph":"X","ts":2233841,"dur":8,"pid":1,"tid":0},
{"name":"Camera::RecalculateView","cat":"function","ph":"X","ts":2235225,"dur":17,"pid":1,"tid":0},
{"name":"Camera::GetForward","cat":"function","ph":"X","ts":2250521,"dur":13,"pid":1,"tid":0},
{"name":"Camera::GetForward","cat":"function","ph":"X","ts":2250541,"dur":2,"pid":1,"tid":0},
{"name":"Camera::RecalculateView","cat":"function","ph":"X","ts":2250548,"dur":8,"pid":1,"tid":0},
{"name":"Camera::GetForward","cat":"function","ph":"X","ts":2267178,"dur":13,"pid":1,"tid":0},
{"name":"Camera::GetForward","cat":"function","ph":"X","ts":2267199,"dur":2,"pid":1,"tid":0},
{"name":"Camera::RecalculateView","cat":"function","ph":"X","ts":2267205,"dur":9,"pid":1,"tid":0},
{"name":"Camera::GetForward","cat":"function","ph":"X","ts":2283845,"dur":14,"pid":1,"tid":0},
{"name":"Camera::GetForward","cat":"function","ph":"X","ts":2283865,"dur":2,"pid":1,"tid":0},
{"name":"Camera::RecalculateView","cat":"function","ph":"X","ts":2283871,"dur":9,"pid":1,"tid":0},
{"name":"Camera::GetForward","cat":"function","ph":"X","ts":2300532,"dur":13,"pid":1,"tid":0},
{"name":"Camera::GetForward","cat":"function","ph":"X","ts":2300553,"dur":2,"pid":1,"tid":0},
{"name":"Camera::RecalculateView","cat":"function","ph":"X","ts":2300558,"dur":9,"pid":1,"tid":0},
{"name":"Camera::GetForward","cat":"function","ph":"X","ts":2317243,"dur":14,"pid":1,"tid":0},
{"name":"Camera::GetForward","cat":"function","ph":"X","ts":2317264,"dur":2,"pid":1,"tid":0},
{"name":"Camera::RecalculateView","cat":"function","ph":"X","ts":2317270,"dur":9,"pid":1,"tid":0},
{"name":"Camera::GetForward","cat":"function","ph":"X","ts":2333870,"dur":12,"pid":1,"tid":0},
{"name":"Camera::GetForward","cat":"function","ph":"X","ts":2333890,"dur":2,"pid":1,"tid":0},
{"name":"Camera::RecalculateView","cat":"function","ph":"X","ts":2333897,"dur":9,"pid":1,"tid":0},
{"name":"Camera::GetForward","cat":"function","ph":"X","ts":2350537,"dur":12,"pid":1,"tid":0},
{"name":"Camera::GetForward","cat":"function","ph":"X","ts":2350556,"dur":2,"pid":1,"tid":0},
{"name":"Camera::RecalculateView","cat":"function","ph":"X","ts":2350562,"dur":9,"pid":1,"tid":0},
{"name":"Camera::GetForward","cat":"function","ph":"X","ts":2367252,"dur":12,"pid":1,"tid":0},
{"name":"Camera::GetForward","cat":"function","ph":"X","ts":2367272,"dur":2,"pid":1,"tid":0},
{"name":"Camera::RecalculateView","cat":"function","ph":"X","ts":2367278,"dur":8,"pid":1,"tid":0},
{"name":"Camera::RecalculateView","cat":"function","ph":"X","ts":2368748,"dur":18,"pid":1,"tid":0},
{"name":"Camera::GetForward","cat":"function","ph":"X","ts":2383906,"dur":11,"pid":1,"tid":0},
{"name":"Camera::GetForward","cat":"function","ph":"X","ts":2383923,"dur":3,"pid":1,"tid":0},
{"name":"Camera::RecalculateView","cat":"function","ph":"X","ts":2383929,"dur":9,"pid":1,"tid":0},
{"name":"Camera::RecalculateView","cat":"function","ph":"X","ts":2385340,"dur":16,"pid":1,"tid":0},
{"name":"Camera::GetForward","cat":"function","ph":"X","ts":2400629,"dur":13,"pid":1,"tid":0},
{"name":"Camera::GetForward","cat":"function","ph":"X","ts":2400649,"dur":2,"pid":1,"tid":0},
{"name":"Camera::RecalculateView","cat":"function","ph":"X","ts":2400655,"dur":9,"pid":1,"tid":0},
{"name":"Camera::RecalculateView","cat":"function","ph":"X","ts":2402289,"dur":18,"pid":1,"tid":0},
{"name":"Camera::GetForward","cat":"function","ph":"X","ts":2417295,"dur":11,"pid":1,"tid":0},
{"name":"Camera::GetForward","cat":"function","ph":"X","ts":2417313,"dur":2,"pid":1,"tid":0},
{"name":"Camera::RecalculateView","cat":"function","ph":"X","ts":2417319,"dur":8,"pid":1,"tid":0},
{"name":"Camera::RecalculateView","cat":"function","ph":"X","ts":2419152,"dur":17,"pid":1,"tid":0},
{"name":"Camera::GetForward","cat":"function","ph":"X","ts":2433956,"dur":11,"pid":1,"tid":0},
{"name":"Camera::RecalculateView","cat":"function","ph":"X","ts":2433973,"dur":8,"pid":1,"tid":0},
{"name":"Camera::RecalculateView","cat":"function","ph":"X","ts":2435357,"dur":16,"pid":1,"tid":0},
{"name":"Camera::GetForward","cat":"function","ph":"X","ts":2450619,"dur":10,"pid":1,"tid":0},
{"name":"Camera::RecalculateView","cat":"function","ph":"X","ts":2450635,"dur":9,"pid":1,"tid":0},
{"name":"Camera::RecalculateView","cat":"function","ph":"X","ts":2451848,"dur":15,"pid":1,"tid":0},
{"name":"Camera::GetForward","cat":"function","ph":"X","ts":2467314,"dur":10,"pid":1,"tid":0},
{"name":"Camera::RecalculateView","cat":"function","ph":"X","ts":2467330,"dur":8,"pid":1,"tid":0},
{"name":"Camera::RecalculateView","cat":"function","ph":"X","ts":2468559,"dur":15,"pid":1,"tid":0},
{"name":"Camera::GetForward","cat":"function","ph":"X","ts":2483970,"dur":10,"pid":1,"tid":0},
{"name":"Camera::RecalculateView","cat":"function","ph":"X","ts":2483985,"dur":8,"pid":1,"tid":0},
{"name":"Camera::RecalculateView","cat":"function","ph":"X","ts":2485139,"dur":15,"pid":1,"tid":0},
{"name":"Camera::GetForward","cat":"function","ph":"X","ts":2500718,"dur":11,"pid":1,"tid":0},
{"name":"Camera::RecalculateView","cat":"function","ph":"X","ts":2500736,"dur":8,"pid":1,"tid":0},
{"name":"Camera::RecalculateView","cat":"function","ph":"X","ts":2502327,"dur":15,"pid":1,"tid":0},
{"name":"Camera::GetForward","cat":"function","ph":"X","ts":2517430,"dur":19,"pid":1,"tid":0},
{"name":"Camera::RecalculateView","cat":"function","ph":"X","ts":2517460,"dur":17,"pid":1,"tid":0},
{"name":"Camera::RecalculateView","cat":"function","ph":"X","ts":2519255,"dur":16,"pid":1,"tid":0},
{"name":"Camera::RecalculateView","cat":"function","ph":"X","ts":2519685,"dur":15,"pid":1,"tid":0},
{"name":"Camera::GetForward","cat":"function","ph":"X","ts":2534083,"dur":11,"pid":1,"tid":0},
{"name":"Camera::RecalculateView","cat":"function","ph":"X","ts":2534101,"dur":8,"pid":1,"tid":0},
{"name":"Camera::RecalculateView","cat":"function","ph":"X","ts":2535583,"dur":16,"pid":1,"tid":0},
{"name":"Camera::GetForward","cat":"function","ph":"X","ts":2550753,"dur":11,"pid":1,"tid":0},
{"name":"Camera::RecalculateView","cat":"function","ph":"X","ts":2550770,"dur":9,"pid":1,"tid":0},
{"name":"Camera::RecalculateView","cat":"function","ph":"X","ts":2552158,"dur":16,"pid":1,"tid":0},
{"name":"Camera::GetForward","cat":"function","ph":"X","ts":2567427,"dur":11,"pid":1,"tid":0},
{"name":"Camera::RecalculateView","cat":"function","ph":"X","ts":2567445,"dur":8,"pid":1,"tid":0},
{"name":"Camera::RecalculateView","cat":"function","ph":"X","ts":2568870,"dur":16,"pid":1,"tid":0},
{"name":"Camera::GetForward","cat":"function","ph":"X","ts":2584117,"dur":12,"pid":1,"tid":0},
{"name":"Camera::RecalculateView","cat":"function","ph":"X","ts":2584135,"dur":9,"pid":1,"tid":0},
{"name":"Camera::RecalculateView","cat":"function","ph":"X","ts":2585500,"dur":16,"pid":1,"tid":0},
{"name":"Camera::GetForward","cat":"function","ph":"X","ts":2600832,"dur":16,"pid":1,"tid":0},
{"name":"Camera::RecalculateView","cat":"function","ph":"X","ts":2600856,"dur":9,"pid":1,"tid":0},
{"name":"Camera::RecalculateView","cat":"function","ph":"X","ts":2602382,"dur":18,"pid":1,"tid":0},
{"name":"Camera::GetForward","cat":"function","ph":"X","ts":2617507,"dur":14,"pid":1,"tid":0},
{"name":"Camera::RecalculateView","cat":"function","ph":"X","ts":2617529,"dur":9,"pid":1,"tid":0},
{"name":"Camera::RecalculateView","cat":"function","ph":"X","ts":2618929,"dur":19,"pid":1,"tid":0},
{"name":"Camera::GetForward","cat":"function","ph":"X","ts":2634202,"dur":12,"pid":1,"tid":0},
{"name":"Camera::RecalculateView","cat":"function","ph":"X","ts":2634221,"dur":9,"pid":1,"tid":0},
{"name":"Camera::RecalculateView","cat":"function","ph":"X","ts":2635719,"dur":17,"pid":1,"tid":0},
{"name":"Camera::GetForward","cat":"function","ph":"X","ts":2650804,"dur":11,"pid":1,"tid":0},
{"name":"Camera::RecalculateView","cat":"function","ph":"X","ts":2650821,"dur":9,"pid":1,"tid":0},
{"name":"Camera::RecalculateView","cat":"function","ph":"X","ts":2652217,"dur":17,"pid":1,"tid":0},
{"name":"Camera::GetForward","cat":"function","ph":"X","ts":2667502,"dur":12,"pid":1,"tid":0},
{"name":"Camera::RecalculateView","cat":"function","ph":"X","ts":2667521,"dur":10,"pid":1,"tid":0},
{"name":"Camera::RecalculateView","cat":"function","ph":"X","ts":2670040,"dur":17,"pid":1,"tid":0},
{"name":"Camera::GetForward","cat":"function","ph":"X","ts":2684166,"dur":11,"pid":1,"tid":0},
{"name":"Camera::RecalculateView","cat":"function","ph":"X","ts":2684184,"dur":16,"pid":1,"tid":0},
{"name":"Camera::RecalculateView","cat":"function","ph":"X","ts":2685598,"dur":16,"pid":1,"tid":0},
{"name":"Camera::GetForward","cat":"function","ph":"X","ts":2700837,"dur":12,"pid":1,"tid":0},
{"name":"Camera::RecalculateView","cat":"function","ph":"X","ts":2700855,"dur":9,"pid":1,"tid":0},
{"name":"Camera::RecalculateView","cat":"function","ph":"X","ts":2702423,"dur":17,"pid":1,"tid":0},
{"name":"Camera::RecalculateView","cat":"function","ph":"X","ts":2703178,"dur":15,"pid":1,"tid":0},
{"name":"Camera::RecalculateView","cat":"function","ph":"X","ts":2703361,"dur":14,"pid":1,"tid":0},
{"name":"Camera::GetForward","cat":"function","ph":"X","ts":2717528,"dur":9,"pid":1,"tid":0},
{"name":"Camera::GetForward","cat":"function","ph":"X","ts":2717543,"dur":2,"pid":1,"tid":0},
{"name":"Camera::RecalculateView","cat":"function","ph":"X","ts":2717548,"dur":8,"pid":1,"tid":0},
{"name":"Camera::RecalculateView","cat":"function","ph":"X","ts":2718797,"dur":15,"pid":1,"tid":0},
{"name":"Camera::RecalculateView","cat":"function","ph":"X","ts":2719452,"dur":14,"pid":1,"tid":0},
{"name":"Camera::GetForward","cat":"function","ph":"X","ts":2734214,"dur":9,"pid":1,"tid":0},
{"name":"Camera::GetForward","cat":"function","ph":"X","ts":2734229,"dur":2,"pid":1,"tid":0},
{"name":"Camera::RecalculateView","cat":"function","ph":"X","ts":2734234,"dur":9,"pid":1,"tid":0},
{"name":"Camera::RecalculateView","cat":"function","ph":"X","ts":2735712,"dur":14,"pid":1,"tid":0},
{"name":"Camera::GetForward","cat":"function","ph":"X","ts":2750871,"dur":9,"pid":1,"tid":0},
{"name":"Camera::GetForward","cat":"function","ph":"X","ts":2750885,"dur":2,"pid":1,"tid":0},
{"name":"Camera::RecalculateView","cat":"function","ph":"X","ts":2750891,"dur":8,"pid":1,"tid":0},
{"name":"Camera::RecalculateView","cat":"function","ph":"X","ts":2752195,"dur":20,"pid":1,"tid":0},
{"name":"Camera::GetForward","cat":"function","ph":"X","ts":2767598,"dur":12,"pid":1,"tid":0},
{"name":"Camera::GetForward","cat":"function","ph":"X","ts":2767803,"dur":2,"pid":1,"tid":0},
{"name":"Camera::RecalculateView","cat":"function","ph":"X","ts":2767809,"dur":8,"pid":1,"tid":0},
{"name":"Camera::RecalculateView","cat":"function","ph":"X","ts":2769365,"dur":17,"pid":1,"tid":0},
{"name":"Camera::GetForward","cat":"function","ph":"X","ts":2784204,"dur":11,"pid":1,"tid":0},
{"name":"Camera::GetForward","cat":"function","ph":"X","ts":2784220,"dur":2,"pid":1,"tid":0},
{"name":"Camera::RecalculateView","cat":"function","ph":"X","ts":2784226,"dur":8,"pid":1,"tid":0},
{"name":"Camera::RecalculateView","cat":"function","ph":"X","ts":2785419,"dur":15,"pid":1,"tid":0},
{"name":"Camera::GetForward","cat":"function","ph":"X","ts":2800927,"dur":11,"pid":1,"tid":0},
{"name":"Camera::GetForward","cat":"function","ph":"X","ts":2800944,"dur":2,"pid":1,"tid":0},
{"name":"Camera::RecalculateView","cat":"function","ph":"X","ts":2800950,"dur":8,"pid":1,"tid":0},
{"name":"Camera::RecalculateView","cat":"function","ph":"X","ts":2802286,"dur":16,"pid":1,"tid":0},
{"name":"Camera::GetForward","cat":"function","ph":"X","ts":2817632,"dur":12,"pid":1,"tid":0},
{"name":"Camera::GetForward","cat":"function","ph":"X","ts":2817650,"dur":2,"pid":1,"tid":0},
{"name":"Camera::RecalculateView","cat":"function","ph":"X","ts":2817656,"dur":9,"pid":1,"tid":0},
{"name":"Camera::RecalculateView","cat":"function","ph":"X","ts":2819211,"dur":17,"pid":1,"tid":0},
{"name":"Camera::GetForward","cat":"function","ph":"X","ts":2834291,"dur":11,"pid":1,"tid":0},
{"name":"Camera::GetForward","cat":"function","ph":"X","ts":2834309,"dur":3,"pid":1,"tid":0},
{"name":"Camera::RecalculateView","cat":"function","ph":"X","ts":2834315,"dur":8,"pid":1,"tid":0},
{"name":"Camera::RecalculateView","cat":"function","ph":"X","ts":2835639,"dur":16,"pid":1,"tid":0},
{"name":"Camera::GetForward","cat":"function","ph":"X","ts":2850987,"dur":10,"pid":1,"tid":0},
{"name":"Camera::GetForward","cat":"function","ph":"X","ts":2851003,"dur":2,"pid":1,"tid":0},
{"name":"Camera::RecalculateView","cat":"function","ph":"X","ts":2851009,"dur":8,"pid":1,"tid":0},
{"name":"Camera::RecalculateView","cat":"function","ph":"X","ts":2852335,"dur":16,"pid":1,"tid":0},
{"name":"Camera::GetForward","cat":"function","ph":"X","ts":2867657,"dur":12,"pid":1,"tid":0},
{"name":"Camera::GetForward","cat":"function","ph":"X","ts":2867675,"dur":2,"pid":1,"tid":0},
{"name":"Camera::RecalculateView","cat":"function","ph":"X","ts":2867681,"dur":8,"pid":1,"tid":0},
{"name":"Camera::RecalculateView","cat":"function","ph":"X","ts":2869105,"dur":16,"pid":1,"tid":0},
{"name":"Camera::GetForward","cat":"function","ph":"X","ts":2884298,"dur":10,"pid":1,"tid":0},
{"name":"Camera::GetForward","cat":"function","ph":"X","ts":2884314,"dur":2,"pid":1,"tid":0},
{"name":"Camera::RecalculateView","cat":"function","ph":"X","ts":2884320,"dur":8,"pid":1,"tid":0},
{"name":"Camera::RecalculateView","cat":"function","ph":"X","ts":2885601,"dur":15,"pid":1,"tid":0},
{"name":"Camera::GetForward","cat":"function","ph":"X","ts":2901007,"dur":11,"pid":1,"tid":0},
{"name":"Camera::GetForward","cat":"function","ph":"X","ts":2901025,"dur":2,"pid":1,"tid":0},
{"name":"Camera::RecalculateView","cat":"function","ph":"X","ts":2901030,"dur":9,"pid":1,"tid":0},
{"name":"Camera::RecalculateView","cat":"function","ph":"X","ts":2902505,"dur":16,"pid":1,"tid":0},
{"name":"Camera::GetForward","cat":"function","ph":"X","ts":2917667,"dur":11,"pid":1,"tid":0},
{"name":"Camera::GetForward","cat":"function","ph":"X","ts":2917684,"dur":2,"pid":1,"tid":0},
{"name":"Camera::RecalculateView","cat":"function","ph":"X","ts":2917689,"dur":8,"pid":1,"tid":0},
{"name":"Camera::RecalculateView","cat":"function","ph":"X","ts":2920058,"dur":16,"pid":1,"tid":0},
{"name":"Camera::RecalculateView","cat":"function","ph":"X","ts":2920583,"dur":14,"pid":1,"tid":0},
{"name":"Camera::GetForward","cat":"function","ph":"X","ts":2934336,"dur":9,"pid":1,"tid":0},
{"name":"Camera::RecalculateView","cat":"function","ph":"X","ts":2934350,"dur":8,"pid":1,"tid":0},
{"name":"Camera::RecalculateView","cat":"function","ph":"X","ts":2935942,"dur":14,"pid":1,"tid":0},
{"name":"Camera::GetForward","cat":"function","ph":"X","ts":2951056,"dur":9,"pid":1,"tid":0},
{"name":"Camera::RecalculateView","cat":"function","ph":"X","ts":2951070,"dur":9,"pid":1,"tid":0},
{"name":"Camera::RecalculateView","cat":"function","ph":"X","ts":2952529,"dur":14,"pid":1,"tid":0},
{"name":"Camera::GetForward","cat":"function","ph":"X","ts":2967707,"dur":9,"pid":1,"tid":0},
{"name":"Camera::RecalculateView","cat":"function","ph":"X","ts":2967723,"dur":9,"pid":1,"tid":0},
{"name":"Camera::RecalculateView","cat":"function","ph":"X","ts":2969128,"dur":15,"pid":1,"tid":0},
{"name":"Camera::GetForward","cat":"function","ph":"X","ts":2984402,"dur":10,"pid":1,"tid":0},
{"name":"Camera::RecalculateView","cat":"function","ph":"X","ts":2984418,"dur":8,"pid":1,"tid":0},
{"name":"Camera::RecalculateView","cat":"function","ph":"X","ts":2986006,"dur":15,"pid":1,"tid":0},
{"name":"Camera::GetForward","cat":"function","ph":"X","ts":3001147,"dur":15,"pid":1,"tid":0},
{"name":"Camera::RecalculateView","cat":"function","ph":"X","ts":3001169,"dur":9,"pid":1,"tid":0},
{"name":"Camera::RecalculateView","cat":"function","ph":"X","ts":3003428,"dur":18,"pid":1,"tid":0},
{"name":"Camera::GetForward","cat":"function","ph":"X","ts":3017820,"dur":14,"pid":1,"tid":0},
{"name":"Camera::RecalculateView","cat":"function","ph":"X","ts":3017842,"dur":9,"pid":1,"tid":0},
{"name":"Camera::RecalculateView","cat":"function","ph":"X","ts":3019520,"dur":19,"pid":1,"tid":0},
{"name":"Camera::GetForward","cat":"function","ph":"X","ts":3034561,"dur":14,"pid":1,"tid":0},
{"name":"Camera::RecalculateView","cat":"function","ph":"X","ts":3034585,"dur":9,"pid":1,"tid":0},
{"name":"Camera::GetForward","cat":"function","ph":"X","ts":3051226,"dur":14,"pid":1,"tid":0},
{"name":"Camera::RecalculateView","cat":"function","ph":"X","ts":3051248,"dur":9,"pid":1,"tid":0},
{"name":"Camera::RecalculateView","cat":"function","ph":"X","ts":3052830,"dur":19,"pid":1,"tid":0},
{"name":"Camera::GetForward","cat":"function","ph":"X","ts":3067859,"dur":14,"pid":1,"tid":0},
{"name":"Camera::RecalculateView","cat":"function","ph":"X","ts":3067880,"dur":9,"pid":1,"tid":0},
{"name":"Camera::RecalculateView","cat":"function","ph":"X","ts":3069240,"dur":18,"pid":1,"tid":0},
{"name":"Camera::GetForward","cat":"function","ph":"X","ts":3084519,"dur":12,"pid":1,"tid":0},
{"name":"Camera::RecalculateView","cat":"function","ph":"X","ts":3084538,"dur":9,"pid":1,"tid":0},
{"name":"Camera::RecalculateView","cat":"function","ph":"X","ts":3086319,"dur":17,"pid":1,"tid":0},
{"name":"Camera::GetForward","cat":"function","ph":"X","ts":3101315,"dur":11,"pid":1,"tid":0},
{"name":"Camera::GetForward","cat":"function","ph":"X","ts":3101334,"dur":2,"pid":1,"tid":0},
{"name":"Camera::RecalculateView","cat":"function","ph":"X","ts":3101339,"dur":8,"pid":1,"tid":0},
{"name":"Camera::RecalculateView","cat":"function","ph":"X","ts":3102812,"dur":17,"pid":1,"tid":0},
{"name":"Camera::GetForward","cat":"function","ph":"X","ts":3117870,"dur":16,"pid":1,"tid":0},
{"name":"Camera::GetForward","cat":"function","ph":"X","ts":3117897,"dur":5,"pid":1,"tid":0},
{"name":"Camera::RecalculateView","cat":"function","ph":"X","ts":3117908,"dur":17,"pid":1,"tid":0},
{"name":"Camera::RecalculateView","cat":"function","ph":"X","ts":3119823,"dur":18,"pid":1,"tid":0},
{"name":"Camera::RecalculateView","cat":"function","ph":"X","ts":3120939,"dur":18,"pid":1,"tid":0},
{"name":"Camera::GetForward","cat":"function","ph":"X","ts":3134530,"dur":11,"pid":1,"tid":0},
{"name":"Camera::RecalculateView","cat":"function","ph":"X","ts":3134548,"dur":9,"pid":1,"tid":0},
{"name":"Camera::RecalculateView","cat":"function","ph":"X","ts":3136296,"dur":16,"pid":1,"tid":0},
{"name":"Camera::GetForward","cat":"function","ph":"X","ts":3151280,"dur":12,"pid":1,"tid":0},
{"name":"Camera::RecalculateView","cat":"function","ph":"X","ts":3151300,"dur":9,"pid":1,"tid":0},
{"name":"Camera::RecalculateView","cat":"function","ph":"X","ts":3152695,"dur":18,"pid":1,"tid":0},
{"name":"Camera::GetForward","cat":"function","ph":"X","ts":3167874,"dur":11,"pid":1,"tid":0},
{"name":"Camera::RecalculateView","cat":"function","ph":"X","ts":3167892,"dur":9,"pid":1,"tid":0},
{"name":"Camera::RecalculateView","cat":"function","ph":"X","ts":3169172,"dur":16,"pid":1,"tid":0},
{"name":"Camera::GetForward","cat":"function","ph":"X","ts":3184561,"dur":11,"pid":1,"tid":0},
{"name":"Camera::RecalculateView","cat":"function","ph":"X","ts":3184578,"dur":9,"pid":1,"tid":0},
{"name":"Camera::RecalculateView","cat":"function","ph":"X","ts":3185837,"dur":16,"pid":1,"tid":0},
{"name":"Camera::GetForward","cat":"function","ph":"X","ts":3201263,"dur":11,"pid":1,"tid":0},
{"name":"Camera::RecalculateView","cat":"function","ph":"X","ts":3201281,"dur":9,"pid":1,"tid":0},
{"name":"Camera::RecalculateView","cat":"function","ph":"X","ts":3203159,"dur":17,"pid":1,"tid":0},
{"name":"Camera::GetForward","cat":"function","ph":"X","ts":3217940,"dur":10,"pid":1,"tid":0},
{"name":"Camera::RecalculateView","cat":"function","ph":"X","ts":3217956,"dur":8,"pid":1,"tid":0},
{"name":"Camera::RecalculateView","cat":"function","ph":"X","ts":3219399,"dur":17,"pid":1,"tid":0},
{"name":"Camera::GetForward","cat":"function","ph":"X","ts":3234645,"dur":12,"pid":1,"tid":0},
{"name":"Camera::RecalculateView","cat":"function","ph":"X","ts":3234664,"dur":9,"pid":1,"tid":0},
{"name":"Camera::RecalculateView","cat":"function","ph":"X","ts":3236174,"dur":20,"pid":1,"tid":0},
{"name":"Camera::GetForward","cat":"function","ph":"X","ts":3251322,"dur":11,"pid":1,"tid":0},
{"name":"Camera::RecalculateView","cat":"function","ph":"X","ts":3251340,"dur":9,"pid":1,"tid":0},
{"name":"Camera::RecalculateView","cat":"function","ph":"X","ts":3252632,"dur":16,"pid":1,"tid":0},
{"name":"Camera::GetForward","cat":"function","ph":"X","ts":3267977,"dur":12,"pid":1,"tid":0},
{"name":"Camera::RecalculateView","cat":"function","ph":"X","ts":3267996,"dur":9,"pid":1,"tid":0},
{"name":"Camera::RecalculateView","cat":"function","ph":"X","ts":3268890,"dur":16,"pid":1,"tid":0},
{"name":"Camera::RecalculateView","cat":"function","ph":"X","ts":3269542,"dur":15,"pid":1,"tid":0},
{"name":"Camera::GetForward","cat":"function","ph":"X","ts":3284659,"dur":12,"pid":1,"tid":0},
{"name":"Camera::GetForward","cat":"function","ph":"X","ts":3284677,"dur":2,"pid":1,"tid":0},
{"name":"Camera::RecalculateView","cat":"function","ph":"X","ts":3284683,"dur":8,"pid":1,"tid":0},
{"name":"Camera::RecalculateView","cat":"function","ph":"X","ts":3285771,"dur":16,"pid":1,"tid":0},
{"name":"Camera::GetForward","cat":"function","ph":"X","ts":3301342,"dur":10,"pid":1,"tid":0},
{"name":"Camera::GetForward","cat":"function","ph":"X","ts":3301359,"dur":3,"pid":1,"tid":0},
{"name":"Camera::RecalculateView","cat":"function","ph":"X","ts":3301365,"dur":8,"pid":1,"tid":0},
{"name":"Camera::RecalculateView","cat":"function","ph":"X","ts":3303005,"dur":15,"pid":1,"tid":0},
{"name":"Camera::GetForward","cat":"function","ph":"X","ts":3318007,"dur":11,"pid":1,"tid":0},
{"name":"Camera::GetForward","cat":"function","ph":"X","ts":3318024,"dur":2,"pid":1,"tid":0},
{"name":"Camera::RecalculateView","cat":"function","ph":"X","ts":3318030,"dur":9,"pid":1,"tid":0},
{"name":"Camera::RecalculateView","cat":"function","ph":"X","ts":3319551,"dur":16,"pid":1,"tid":0},
{"name":"Camera::GetForward","cat":"function","ph":"X","ts":3334840,"dur":11,"pid":1,"tid":0},
{"name":"Camera::GetForward","cat":"function","ph":"X","ts":3334858,"dur":2,"pid":1,"tid":0},
{"name":"Camera::RecalculateView","cat":"function","ph":"X","ts":3334863,"dur":8,"pid":1,"tid":0},
{"name":"Camera::RecalculateView","cat":"function","ph":"X","ts":3336347,"dur":16,"pid":1,"tid":0},
{"name":"Camera::GetForward","cat":"function","ph":"X","ts":3351420,"dur":13,"pid":1,"tid":0},
{"name":"Camera::GetForward","cat":"function","ph":"X","ts":3351440,"dur":2,"pid":1,"tid":0},
{"name":"Camera::RecalculateView","cat":"function","ph":"X","ts":3351447,"dur":9,"pid":1,"tid":0},
{"name":"Camera::RecalculateView","cat":"function","ph":"X","ts":3352805,"dur":16,"pid":1,"tid":0},
{"name":"Camera::GetForward","cat":"function","ph":"X","ts":3368069,"dur":11,"pid":1,"tid":0},
{"name":"Camera::GetForward","cat":"function","ph":"X","ts":3368086,"dur":2,"pid":1,"tid":0},
{"name":"Camera::RecalculateView","cat":"function","ph":"X","ts":3368092,"dur":8,"pid":1,"tid":0},
{"name":"Camera::RecalculateView","cat":"function","ph":"X","ts":3369667,"dur":20,"pid":1,"tid":0},
{"name":"Camera::GetForward","cat":"function","ph":"X","ts":3384925,"dur":25,"pid":1,"tid":0},
{"name":"Camera::GetForward","cat":"function","ph":"X","ts":3384963,"dur":5,"pid":1,"tid":0},
{"name":"Camera::RecalculateView","cat":"function","ph":"X","ts":3384974,"dur":17,"pid":1,"tid":0},
{"name":"Camera::RecalculateView","cat":"function","ph":"X","ts":3387040,"dur":19,"pid":1,"tid":0},
{"name":"Camera::GetForward","cat":"function","ph":"X","ts":3401453,"dur":14,"pid":1,"tid":0},
{"name":"Camera::GetForward","cat":"function","ph":"X","ts":3401475,"dur":2,"pid":1,"tid":0},
{"name":"Camera::RecalculateView","cat":"function","ph":"X","ts":3401480,"dur":8,"pid":1,"tid":0},
{"name":"Camera::RecalculateView","cat":"function","ph":"X","ts":3402919,"dur":18,"pid":1,"tid":0},
{"name":"Camera::GetForward","cat":"function","ph":"X","ts":3418147,"dur":15,"pid":1,"tid":0},
{"name":"Camera::GetForward","cat":"function","ph":"X","ts":3418170,"dur":3,"pid":1,"tid":0},
{"name":"Camera::RecalculateView","cat":"function","ph":"X","ts":3418176,"dur":9,"pid":1,"tid":0},
{"name":"Camera::RecalculateView","cat":"function","ph":"X","ts":3419498,"dur":19,"pid":1,"tid":0},
{"name":"Camera::GetForward","cat":"function","ph":"X","ts":3434784,"dur":12,"pid":1,"tid":0},
{"name":"Camera::GetForward","cat":"function","ph":"X","ts":3434803,"dur":2,"pid":1,"tid":0},
{"name":"Camera::RecalculateView","cat":"function","ph":"X","ts":3434809,"dur":8,"pid":1,"tid":0},
{"name":"Camera::RecalculateView","cat":"function","ph":"X","ts":3436094,"dur":17,"pid":1,"tid":0},
{"name":"Camera::GetForward","cat":"function","ph":"X","ts":3451487,"dur":11,"pid":1,"tid":0},
{"name":"Camera::GetForward","cat":"function","ph":"X","ts":3451506,"dur":2,"pid":1,"tid":0},
{"name":"Camera::RecalculateView","cat":"function","ph":"X","ts":3451511,"dur":8,"pid":1,"tid":0},
{"name":"Camera::RecalculateView","cat":"function","ph":"X","ts":3452818,"dur":17,"pid":1,"tid":0},
{"name":"Camera::GetForward","cat":"function","ph":"X","ts":3468097,"dur":11,"pid":1,"tid":0},
{"name":"Camera::GetForward","cat":"function","ph":"X","ts":3468114,"dur":2,"pid":1,"tid":0},
{"name":"Camera::RecalculateView","cat":"function","ph":"X","ts":3468119,"dur":8,"pid":1,"tid":0},
{"name":"Camera::RecalculateView","cat":"function","ph":"X","ts":3469181,"dur":16,"pid":1,"tid":0},
{"name":"Camera::GetForward","cat":"function","ph":"X","ts":3484797,"dur":11,"pid":1,"tid":0},
{"name":"Camera::GetForward","cat":"function","ph":"X","ts":3484814,"dur":2,"pid":1,"tid":0},
{"name":"Camera::RecalculateView","cat":"function","ph":"X","ts":3484820,"dur":8,"pid":1,"tid":0},
{"name":"Camera::GetForward","cat":"function","ph":"X","ts":3501499,"dur":11,"pid":1,"tid":0},
{"name":"Camera::RecalculateView","cat":"function","ph":"X","ts":3501516,"dur":8,"pid":1,"tid":0},
{"name":"Camera::GetForward","cat":"function","ph":"X","ts":3518172,"dur":12,"pid":1,"tid":0},
{"name":"Camera::RecalculateView","cat":"function","ph":"X","ts":3518191,"dur":8,"pid":1,"tid":0},
{"name":"Camera::GetForward","cat":"function","ph":"X","ts":3534870,"dur":12,"pid":1,"tid":0},
{"name":"Camera::RecalculateView","cat":"function","ph":"X","ts":3534889,"dur":8,"pid":1,"tid":0},
{"name":"Camera::GetForward","cat":"function","ph":"X","ts":3551620,"dur":12,"pid":1,"tid":0},
{"name":"Camera::RecalculateView","cat":"function","ph":"X","ts":3551639,"dur":8,"pid":1,"tid":0},
{"name":"Camera::GetForward","cat":"function","ph":"X","ts":3568194,"dur":12,"pid":1,"tid":0},
{"name":"Camera::RecalculateView","cat":"function","ph":"X","ts":3568213,"dur":9,"pid":1,"tid":0},
{"name":"Camera::GetForward","cat":"function","ph":"X","ts":3584890,"dur":11,"pid":1,"tid":0},
{"name":"Camera::RecalculateView","cat":"function","ph":"X","ts":3584909,"dur":8,"pid":1,"tid":0},
{"name":"Camera::RecalculateView","cat":"function","ph":"X","ts":3586034,"dur":16,"pid":1,"tid":0},
{"name":"Camera::GetForward","cat":"function","ph":"X","ts":3601580,"dur":11,"pid":1,"tid":0},
{"name":"Camera::RecalculateView","cat":"function","ph":"X","ts":3601597,"dur":8,"pid":1,"tid":0},
{"name":"Camera::GetForward","cat":"function","ph":"X","ts":3618246,"dur":13,"pid":1,"tid":0},
{"name":"Camera::RecalculateView","cat":"function","ph":"X","ts":3618266,"dur":9,"pid":1,"tid":0},
{"name":"Camera::RecalculateView","cat":"function","ph":"X","ts":3620637,"dur":17,"pid":1,"tid":0},
{"name":"Camera::GetForward","cat":"function","ph":"X","ts":3634978,"dur":12,"pid":1,"tid":0},
{"name":"Camera::RecalculateView","cat":"function","ph":"X","ts":3634997,"dur":9,"pid":1,"tid":0},
{"name":"Camera::RecalculateView","cat":"function","ph":"X","ts":3636312,"dur":17,"pid":1,"tid":0},
{"name":"Camera::GetForward","cat":"function","ph":"X","ts":3651711,"dur":12,"pid":1,"tid":0},
{"name":"Camera::RecalculateView","cat":"function","ph":"X","ts":3651731,"dur":8,"pid":1,"tid":0},
{"name":"Camera::RecalculateView","cat":"function","ph":"X","ts":3653005,"dur":17,"pid":1,"tid":0},
{"name":"Camera::GetForward","cat":"function","ph":"X","ts":3668349,"dur":11,"pid":1,"tid":0},
{"name":"Camera::RecalculateView","cat":"function","ph":"X","ts":3668367,"dur":8,"pid":1,"tid":0},
{"name":"Camera::RecalculateView","cat":"function","ph":"X","ts":3669859,"dur":146,"pid":1,"tid":0},
{"name":"Camera::GetForward","cat":"function","ph":"X","ts":3684977,"dur":11,"pid":1,"tid":0},
{"name":"Camera::RecalculateView","cat":"function","ph":"X","ts":3684994,"dur":9,"pid":1,"tid":0},
{"name":"Camera::RecalculateView","cat":"function","ph":"X","ts":3686294,"dur":15,"pid":1,"tid":0},
{"name":"Camera::GetForward","cat":"function","ph":"X","ts":3701670,"dur":11,"pid":1,"tid":0},
{"name":"Camera::RecalculateView","cat":"function","ph":"X","ts":3701689,"dur":8,"pid":1,"tid":0},
{"name":"Camera::RecalculateView","cat":"function","ph":"X","ts":3702668,"dur":15,"pid":1,"tid":0},
{"name":"Camera::GetForward","cat":"function","ph":"X","ts":3718316,"dur":11,"pid":1,"tid":0},
{"name":"Camera::RecalculateView","cat":"function","ph":"X","ts":3718333,"dur":9,"pid":1,"tid":0},
{"name":"Camera::RecalculateView","cat":"function","ph":"X","ts":3719708,"dur":16,"pid":1,"tid":0},
{"name":"Camera::GetForward","cat":"function","ph":"X","ts":3735012,"dur":10,"pid":1,"tid":0},
{"name":"Camera::RecalculateView","cat":"function","ph":"X","ts":3735029,"dur":9,"pid":1,"tid":0},
{"name":"Camera::RecalculateView","cat":"function","ph":"X","ts":3737089,"dur":15,"pid":1,"tid":0},
{"name":"Camera::RecalculateView","cat":"function","ph":"X","ts":3751808,"dur":15,"pid":1,"tid":0},
{"name":"Camera::RecalculateView","cat":"function","ph":"X","ts":3753039,"dur":15,"pid":1,"tid":0},
{"name":"Camera::RecalculateView","cat":"function","ph":"X","ts":3768458,"dur":15,"pid":1,"tid":0},
{"name":"Camera::RecalculateView","cat":"function","ph":"X","ts":3769758,"dur":15,"pid":1,"tid":0},
{"name":"Camera::RecalculateView","cat":"function","ph":"X","ts":3785068,"dur":16,"pid":1,"tid":0},
{"name":"Camera::RecalculateView","cat":"function","ph":"X","ts":3786355,"dur":15,"pid":1,"tid":0},
{"name":"Camera::RecalculateView","cat":"function","ph":"X","ts":3801765,"dur":16,"pid":1,"tid":0},
{"name":"Camera::RecalculateView","cat":"function","ph":"X","ts":3802703,"dur":14,"pid":1,"tid":0},
{"name":"Camera::RecalculateView","cat":"function","ph":"X","ts":3818418,"dur":16,"pid":1,"tid":0},
{"name":"Camera::RecalculateView","cat":"function","ph":"X","ts":3819354,"dur":19,"pid":1,"tid":0},
{"name":"Camera::RecalculateView","cat":"function","ph":"X","ts":3835299,"dur":32,"pid":1,"tid":0},
{"name":"Camera::RecalculateView","cat":"function","ph":"X","ts":3836465,"dur":17,"pid":1,"tid":0},
{"name":"Camera::RecalculateView","cat":"function","ph":"X","ts":3851862,"dur":22,"pid":1,"tid":0},
{"name":"Camera::RecalculateView","cat":"function","ph":"X","ts":3868493,"dur":20,"pid":1,"tid":0},
{"name":"Camera::RecalculateView","cat":"function","ph":"X","ts":3885158,"dur":19,"pid":1,"tid":0},
{"name":"Camera::RecalculateView","cat":"function","ph":"X","ts":3901811,"dur":19,"pid":1,"tid":0},
{"name":"Camera::RecalculateView","cat":"function","ph":"X","ts":3903242,"dur":18,"pid":1,"tid":0},
{"name":"Camera::RecalculateView","cat":"function","ph":"X","ts":3903684,"dur":14,"pid":1,"tid":0},
{"name":"Camera::RecalculateView","cat":"function","ph":"X","ts":3918571,"dur":29,"pid":1,"tid":0},
{"name":"Camera::RecalculateView","cat":"function","ph":"X","ts":3920251,"dur":18,"pid":1,"tid":0},
{"name":"Camera::RecalculateView","cat":"function","ph":"X","ts":3935227,"dur":20,"pid":1,"tid":0},
{"name":"Camera::RecalculateView","cat":"function","ph":"X","ts":3936677,"dur":16,"pid":1,"tid":0},
{"name":"Camera::RecalculateView","cat":"function","ph":"X","ts":3951915,"dur":17,"pid":1,"tid":0},
{"name":"Camera::RecalculateView","cat":"function","ph":"X","ts":3953332,"dur":16,"pid":1,"tid":0},
{"name":"Camera::RecalculateView","cat":"function","ph":"X","ts":3968660,"dur":17,"pid":1,"tid":0},
{"name":"Camera::RecalculateView","cat":"function","ph":"X","ts":3970063,"dur":16,"pid":1,"tid":0},
{"name":"Camera::RecalculateView","cat":"function","ph":"X","ts":3985197,"dur":16,"pid":1,"tid":0},
{"name":"Camera::RecalculateView","cat":"function","ph":"X","ts":3986700,"dur":34,"pid":1,"tid":0},
{"name":"Camera::RecalculateView","cat":"function","ph":"X","ts":4001913,"dur":16,"pid":1,"tid":0},
{"name":"Camera::RecalculateView","cat":"function","ph":"X","ts":4003156,"dur":15,"pid":1,"tid":0},
{"name":"Camera::RecalculateView","cat":"function","ph":"X","ts":4018581,"dur":17,"pid":1,"tid":0},
{"name":"Camera::RecalculateView","cat":"function","ph":"X","ts":4020228,"dur":16,"pid":1,"tid":0},
{"name":"Camera::RecalculateView","cat":"function","ph":"X","ts":4035284,"dur":20,"pid":1,"tid":0},
{"name":"Camera::RecalculateView","cat":"function","ph":"X","ts":4051975,"dur":17,"pid":1,"tid":0},
{"name":"Camera::RecalculateView","cat":"function","ph":"X","ts":4068677,"dur":19,"pid":1,"tid":0},
{"name":"Camera::RecalculateView","cat":"function","ph":"X","ts":4085357,"dur":19,"pid":1,"tid":0},
{"name":"Camera::RecalculateView","cat":"function","ph":"X","ts":4101956,"dur":17,"pid":1,"tid":0},
{"name":"Camera::RecalculateView","cat":"function","ph":"X","ts":4118656,"dur":18,"pid":1,"tid":0},
{"name":"Camera::RecalculateView","cat":"function","ph":"X","ts":4135351,"dur":23,"pid":1,"tid":0},
{"name":"Camera::RecalculateView","cat":"function","ph":"X","ts":4152049,"dur":20,"pid":1,"tid":0},
{"name":"Camera::RecalculateView","cat":"function","ph":"X","ts":4168704,"dur":19,"pid":1,"tid":0},
{"name":"Camera::RecalculateView","cat":"function","ph":"X","ts":4185397,"dur":18,"pid":1,"tid":0},
{"name":"Camera::RecalculateView","cat":"function","ph":"X","ts":4202059,"dur":18,"pid":1,"tid":0},
{"name":"Camera::RecalculateView","cat":"function","ph":"X","ts":4218739,"dur":19,"pid":1,"tid":0},
{"name":"Camera::RecalculateView","cat":"function","ph":"X","ts":4235423,"dur":20,"pid":1,"tid":0},
{"name":"Camera::RecalculateView","cat":"function","ph":"X","ts":4252172,"dur":20,"pid":1,"tid":0},
{"name":"Camera::RecalculateView","cat":"function","ph":"X","ts":4268921,"dur":32,"pid":1,"tid":0},
{"name":"Camera::RecalculateView","cat":"function","ph":"X","ts":4285498,"dur":21,"pid":1,"tid":0},
{"name":"Camera::RecalculateView","cat":"function","ph":"X","ts":4302175,"dur":22,"pid":1,"tid":0},
{"name":"Camera::RecalculateView","cat":"function","ph":"X","ts":4318863,"dur":20,"pid":1,"tid":0},
{"name":"Camera::RecalculateView","cat":"function","ph":"X","ts":4335524,"dur":23,"pid":1,"tid":0},
{"name":"Camera::RecalculateView","cat":"function","ph":"X","ts":4352198,"dur":20,"pid":1,"tid":0},
{"name":"Camera::RecalculateView","cat":"function","ph":"X","ts":4369049,"dur":36,"pid":1,"tid":0},
{"name":"Camera::RecalculateView","cat":"function","ph":"X","ts":4385587,"dur":19,"pid":1,"tid":0},
{"name":"Camera::RecalculateView","cat":"function","ph":"X","ts":4402212,"dur":20,"pid":1,"tid":0},
{"name":"Camera::RecalculateView","cat":"function","ph":"X","ts":4418877,"dur":20,"pid":1,"tid":0},
{"name":"Camera::RecalculateView","cat":"function","ph":"X","ts":4435615,"dur":19,"pid":1,"tid":0},
{"name":"Camera::RecalculateView","cat":"function","ph":"X","ts":4452269,"dur":20,"pid":1,"tid":0},
{"name":"Camera::RecalculateView","cat":"function","ph":"X","ts":4469054,"dur":19,"pid":1,"tid":0},
{"name":"Camera::RecalculateView","cat":"function","ph":"X","ts":4485700,"dur":32,"pid":1,"tid":0},
{"name":"Camera::RecalculateView","cat":"function","ph":"X","ts":4502302,"dur":20,"pid":1,"tid":0},
{"name":"Camera::RecalculateView","cat":"function","ph":"X","ts":4519037,"dur":19,"pid":1,"tid":0},
{"name":"Camera::RecalculateView","cat":"function","ph":"X","ts":4535667,"dur":19,"pid":1,"tid":0},
{"name":"Camera::RecalculateView","cat":"function","ph":"X","ts":4552316,"dur":18,"pid":1,"tid":0},
{"name":"Camera::RecalculateView","cat":"function","ph":"X","ts":4569047,"dur":19,"pid":1,"tid":0},
{"name":"Camera::RecalculateView","cat":"function","ph":"X","ts":4585788,"dur":51,"pid":1,"tid":0},
{"name":"Camera::RecalculateView","cat":"function","ph":"X","ts":4602376,"dur":18,"pid":1,"tid":0},
{"name":"Camera::RecalculateView","cat":"function","ph":"X","ts":4619055,"dur":19,"pid":1,"tid":0},
{"name":"Camera::RecalculateView","cat":"function","ph":"X","ts":4635724,"dur":19,"pid":1,"tid":0},
{"name":"Camera::RecalculateView","cat":"function","ph":"X","ts":4652431,"dur":21,"pid":1,"tid":0},
{"name":"Camera::RecalculateView","cat":"function","ph":"X","ts":4669128,"dur":21,"pid":1,"tid":0},
{"name":"Camera::RecalculateView","cat":"function","ph":"X","ts":4685821,"dur":21,"pid":1,"tid":0},
{"name":"Camera::RecalculateView","cat":"function","ph":"X","ts":4702444,"dur":20,"pid":1,"tid":0},
{"name":"Camera::RecalculateView","cat":"function","ph":"X","ts":4719150,"dur":21,"pid":1,"tid":0},
{"name":"Camera::RecalculateView","cat":"function","ph":"X","ts":4735860,"dur":20,"pid":1,"tid":0},
{"name":"Camera::RecalculateView","cat":"function","ph":"X","ts":4752491,"dur":19,"pid":1,"tid":0},
{"name":"Camera::RecalculateView","cat":"function","ph":"X","ts":4769218,"dur":19,"pid":1,"tid":0},
{"name":"Camera::RecalculateView","cat":"function","ph":"X","ts":4785910,"dur":32,"pid":1,"tid":0},
{"name":"Camera::RecalculateView","cat":"function","ph":"X","ts":4802554,"dur":18,"pid":1,"tid":0},
{"name":"Camera::RecalculateView","cat":"function","ph":"X","ts":4819207,"dur":18,"pid":1,"tid":0},
{"name":"Camera::RecalculateView","cat":"function","ph":"X","ts":4835918,"dur":17,"pid":1,"tid":0},
{"name":"Camera::RecalculateView","cat":"function","ph":"X","ts":4852650,"dur":20,"pid":1,"tid":0},
{"name":"Camera::RecalculateView","cat":"function","ph":"X","ts":4869324,"dur":22,"pid":1,"tid":0},
{"name":"Camera::RecalculateView","cat":"function","ph":"X","ts":4885975,"dur":20,"pid":1,"tid":0},
{"name":"Camera::RecalculateView","cat":"function","ph":"X","ts":4902608,"dur":20,"pid":1,"tid":0},
{"name":"Camera::RecalculateView","cat":"function","ph":"X","ts":4919331,"dur":21,"pid":1,"tid":0},
{"name":"Camera::RecalculateView","cat":"function","ph":"X","ts":4935981,"dur":19,"pid":1,"tid":0},
{"name":"Camera::RecalculateView","cat":"function","ph":"X","ts":4952707,"dur":20,"pid":1,"tid":0},
{"name":"Camera::RecalculateView","cat":"function","ph":"X","ts":4969345,"dur":19,"pid":1,"tid":0},
{"name":"Camera::RecalculateView","cat":"function","ph":"X","ts":4986041,"dur":19,"pid":1,"tid":0},
{"name":"Camera::RecalculateView","cat":"function","ph":"X","ts":5002747,"dur":19,"pid":1,"tid":0},
{"name":"Camera::RecalculateView","cat":"function","ph":"X","ts":5019458,"dur":20,"pid":1,"tid":0},
{"name":"Camera::RecalculateView","cat":"function","ph":"X","ts":5036055,"dur":18,"pid":1,"tid":0},
{"name":"Camera::RecalculateView","cat":"function","ph":"X","ts":5052735,"dur":19,"pid":1,"tid":0},
{"name":"Camera::RecalculateView","cat":"function","ph":"X","ts":5069527,"dur":24,"pid":1,"tid":0},
{"name":"Camera::RecalculateView","cat":"function","ph":"X","ts":5086247,"dur":22,"pid":1,"tid":0},
{"name":"Camera::RecalculateView","cat":"function","ph":"X","ts":5102823,"dur":23,"pid":1,"tid":0},
{"name":"Camera::RecalculateView","cat":"function","ph":"X","ts":5119522,"dur":23,"pid":1,"tid":0},
{"name":"Camera::RecalculateView","cat":"function","ph":"X","ts":5136170,"dur":21,"pid":1,"tid":0},
{"name":"Camera::RecalculateView","cat":"function","ph":"X","ts":5152884,"dur":23,"pid":1,"tid":0},
{"name":"Camera::RecalculateView","cat":"function","ph":"X","ts":5169548,"dur":22,"pid":1,"tid":0},
{"name":"Camera::RecalculateView","cat":"function","ph":"X","ts":5186237,"dur":22,"pid":1,"tid":0},
{"name":"Camera::RecalculateView","cat":"function","ph":"X","ts":5202986,"dur":21,"pid":1,"tid":0},
{"name":"Camera::RecalculateView","cat":"function","ph":"X","ts":5219575,"dur":20,"pid":1,"tid":0},
{"name":"Camera::RecalculateView","cat":"function","ph":"X","ts":5236237,"dur":21,"pid":1,"tid":0},
{"name":"Camera::RecalculateView","cat":"function","ph":"X","ts":5252920,"dur":21,"pid":1,"tid":0},
{"name":"Camera::RecalculateView","cat":"function","ph":"X","ts":5269660,"dur":23,"pid":1,"tid":0},
{"name":"Camera::RecalculateView","cat":"function","ph":"X","ts":5286288,"dur":20,"pid":1,"tid":0},
{"name":"Camera::RecalculateView","cat":"function","ph":"X","ts":5302981,"dur":21,"pid":1,"tid":0},
{"name":"Camera::RecalculateView","cat":"function","ph":"X","ts":5319656,"dur":20,"pid":1,"tid":0},
{"name":"Camera::RecalculateView","cat":"function","ph":"X","ts":5336298,"dur":19,"pid":1,"tid":0},
{"name":"Camera::RecalculateView","cat":"function","ph":"X","ts":5353002,"dur":20,"pid":1,"tid":0},
{"name":"Camera::RecalculateView","cat":"function","ph":"X","ts":5369669,"dur":20,"pid":1,"tid":0},
{"name":"Camera::RecalculateView","cat":"function","ph":"X","ts":5386392,"dur":20,"pid":1,"tid":0},
{"name":"Camera::RecalculateView","cat":"function","ph":"X","ts":5403053,"dur":20,"pid":1,"tid":0},
{"name":"Camera::RecalculateView","cat":"function","ph":"X","ts":5419722,"dur":19,"pid":1,"tid":0},
{"name":"Camera::RecalculateView","cat":"function","ph":"X","ts":5436456,"dur":19,"pid":1,"tid":0},
{"name":"Camera::RecalculateView","cat":"function","ph":"X","ts":5453067,"dur":20,"pid":1,"tid":0},
{"name":"Camera::RecalculateView","cat":"function","ph":"X","ts":5469807,"dur":21,"pid":1,"tid":0},
{"name":"Camera::RecalculateView","cat":"function","ph":"X","ts":5486461,"dur":20,"pid":1,"tid":0},
{"name":"Camera::RecalculateView","cat":"function","ph":"X","ts":5503143,"dur":19,"pid":1,"tid":0},
{"name":"Camera::RecalculateView","cat":"function","ph":"X","ts":5519788,"dur":22,"pid":1,"tid":0},
{"name":"Camera::RecalculateView","cat":"function","ph":"X","ts":5536473,"dur":19,"pid":1,"tid":0},
{"name":"Camera::RecalculateView","cat":"function","ph":"X","ts":5553185,"dur":32,"pid":1,"tid":0},
{"name":"Camera::RecalculateView","cat":"function","ph":"X","ts":5569908,"dur":24,"pid":1,"tid":0},
{"name":"Camera::RecalculateView","cat":"function","ph":"X","ts":5586521,"dur":19,"pid":1,"tid":0},
{"name":"Camera::RecalculateView","cat":"function","ph":"X","ts":5603220,"dur":19,"pid":1,"tid":0},
{"name":"Camera::RecalculateView","cat":"function","ph":"X","ts":5619897,"dur":19,"pid":1,"tid":0},
{"name":"Camera::RecalculateView","cat":"function","ph":"X","ts":5636534,"dur":19,"pid":1,"tid":0},
{"name":"Camera::RecalculateView","cat":"function","ph":"X","ts":5653221,"dur":19,"pid":1,"tid":0},
{"name":"Camera::RecalculateView","cat":"function","ph":"X","ts":5669974,"dur":20,"pid":1,"tid":0},
{"name":"Camera::RecalculateView","cat":"function","ph":"X","ts":5686613,"dur":22,"pid":1,"tid":0},
{"name":"Camera::RecalculateView","cat":"function","ph":"X","ts":5703280,"dur":20,"pid":1,"tid":0}
]
}
